{
 "@context": "http://iiif.io/api/presentation/3/context.json",
 "id": "iiif/annotations/A16098000171.json",
 "type": "AnnotationPage",
 "items": [
  {
   "@context": "http://iiif.io/api/presentation/3/context.json",
   "id": "https://data.goldenagents.org/datasets/dh2020/annotation/A16098000171/r1l1",
   "type": "Annotation",
   "motivation": "supplementing",
   "body": [
    {
     "type": "TextualBody",
     "language": "nl",
     "value": "36"
    }
   ],
   "target": {
    "id": "https://data.goldenagents.org/datasets/dh2020/canvas/A16098000171",
    "selector": {
     "type": "SvgSelector",
     "value": "<svg xmlns=\"http://www.w3.org/2000/svg\"><path fill-rule=\"evenodd\" fill=\"#66cc99\" stroke=\"#555555\" stroke-width=\"1\" fill-opacity=\"0.08\" d=\"M 488,300 L 513,299 L 538,298 L 563,298 L 588,299 L 614,302 L 614,152 L 588,149 L 563,148 L 538,148 L 513,149 L 488,150 L 488,300 Z\"/></svg>"
    }
   }
  },
  {
   "@context": "http://iiif.io/api/presentation/3/context.json",
   "id": "https://data.goldenagents.org/datasets/dh2020/annotation/A16098000171/r2l1",
   "type": "Annotation",
   "motivation": "supplementing",
   "body": [
    {
     "type": "TextualBody",
     "language": "nl",
     "value": "Een eike trecktaaffel met een"
    }
   ],
   "target": {
    "id": "https://data.goldenagents.org/datasets/dh2020/canvas/A16098000171",
    "selector": {
     "type": "SvgSelector",
     "value": "<svg xmlns=\"http://www.w3.org/2000/svg\"><path fill-rule=\"evenodd\" fill=\"#66cc99\" stroke=\"#555555\" stroke-width=\"1\" fill-opacity=\"0.08\" d=\"M 874,297 L 936,296 L 999,295 L 1061,293 L 1124,293 L 1187,292 L 1249,291 L 1312,291 L 1374,291 L 1437,293 L 1500,293 L 1562,293 L 1625,293 L 1687,295 L 1750,296 L 1813,297 L 1875,298 L 1938,299 L 2000,301 L 2063,301 L 2126,303 L 2126,257 L 2063,255 L 2000,255 L 1938,253 L 1875,252 L 1813,251 L 1750,250 L 1687,249 L 1625,247 L 1562,247 L 1500,247 L 1437,247 L 1374,245 L 1312,245 L 1249,245 L 1187,246 L 1124,247 L 1061,247 L 999,249 L 936,250 L 874,251 L 874,297 Z\"/></svg>"
    }
   }
  },
  {
   "@context": "http://iiif.io/api/presentation/3/context.json",
   "id": "https://data.goldenagents.org/datasets/dh2020/annotation/A16098000171/r2l2",
   "type": "Annotation",
   "motivation": "supplementing",
   "body": [
    {
     "type": "TextualBody",
     "language": "nl",
     "value": "Turcx kleet"
    }
   ],
   "target": {
    "id": "https://data.goldenagents.org/datasets/dh2020/canvas/A16098000171",
    "selector": {
     "type": "SvgSelector",
     "value": "<svg xmlns=\"http://www.w3.org/2000/svg\"><path fill-rule=\"evenodd\" fill=\"#66cc99\" stroke=\"#555555\" stroke-width=\"1\" fill-opacity=\"0.08\" d=\"M 1148,349 L 1173,352 L 1198,353 L 1223,354 L 1249,355 L 1274,357 L 1299,357 L 1325,359 L 1350,359 L 1375,359 L 1400,360 L 1426,361 L 1451,361 L 1476,361 L 1502,361 L 1527,361 L 1552,362 L 1578,363 L 1578,317 L 1552,316 L 1527,315 L 1502,315 L 1476,315 L 1451,315 L 1426,315 L 1400,314 L 1375,313 L 1350,313 L 1325,313 L 1299,311 L 1274,311 L 1249,309 L 1223,308 L 1198,307 L 1173,306 L 1148,303 L 1148,349 Z\"/></svg>"
    }
   }
  },
  {
   "@context": "http://iiif.io/api/presentation/3/context.json",
   "id": "https://data.goldenagents.org/datasets/dh2020/annotation/A16098000171/r2l4",
   "type": "Annotation",
   "motivation": "supplementing",
   "body": [
    {
     "type": "TextualBody",
     "language": "nl",
     "value": "Linnen"
    }
   ],
   "target": {
    "id": "https://data.goldenagents.org/datasets/dh2020/canvas/A16098000171",
    "selector": {
     "type": "SvgSelector",
     "value": "<svg xmlns=\"http://www.w3.org/2000/svg\"><path fill-rule=\"evenodd\" fill=\"#66cc99\" stroke=\"#555555\" stroke-width=\"1\" fill-opacity=\"0.08\" d=\"M 1256,474 L 1281,474 L 1307,475 L 1332,476 L 1358,476 L 1383,478 L 1409,480 L 1434,480 L 1460,481 L 1486,483 L 1511,485 L 1537,486 L 1562,487 L 1588,488 L 1613,489 L 1639,490 L 1664,490 L 1690,490 L 1716,490 L 1716,442 L 1690,442 L 1664,442 L 1639,442 L 1613,441 L 1588,440 L 1562,439 L 1537,438 L 1511,437 L 1486,435 L 1460,433 L 1434,432 L 1409,432 L 1383,430 L 1358,428 L 1332,428 L 1307,427 L 1281,426 L 1256,426 L 1256,474 Z\"/></svg>"
    }
   }
  },
  {
   "@context": "http://iiif.io/api/presentation/3/context.json",
   "id": "https://data.goldenagents.org/datasets/dh2020/annotation/A16098000171/r2l5",
   "type": "Annotation",
   "motivation": "supplementing",
   "body": [
    {
     "type": "TextualBody",
     "language": "nl",
     "value": "Sesendertigh linne lakens, seventien"
    }
   ],
   "target": {
    "id": "https://data.goldenagents.org/datasets/dh2020/canvas/A16098000171",
    "selector": {
     "type": "SvgSelector",
     "value": "<svg xmlns=\"http://www.w3.org/2000/svg\"><path fill-rule=\"evenodd\" fill=\"#66cc99\" stroke=\"#555555\" stroke-width=\"1\" fill-opacity=\"0.08\" d=\"M 824,626 L 893,622 L 962,618 L 1031,618 L 1100,616 L 1169,616 L 1238,617 L 1307,618 L 1376,619 L 1445,622 L 1514,624 L 1583,626 L 1652,628 L 1721,630 L 1790,634 L 1859,636 L 1928,638 L 1997,638 L 2066,640 L 2135,640 L 2204,640 L 2204,592 L 2135,592 L 2066,592 L 1997,590 L 1928,590 L 1859,588 L 1790,586 L 1721,582 L 1652,580 L 1583,578 L 1514,576 L 1445,574 L 1376,571 L 1307,570 L 1238,569 L 1169,568 L 1100,568 L 1031,570 L 962,570 L 893,574 L 824,578 L 824,626 Z\"/></svg>"
    }
   }
  },
  {
   "@context": "http://iiif.io/api/presentation/3/context.json",
   "id": "https://data.goldenagents.org/datasets/dh2020/annotation/A16098000171/r2l6",
   "type": "Annotation",
   "motivation": "supplementing",
   "body": [
    {
     "type": "TextualBody",
     "language": "nl",
     "value": "van seven ellen, ende tnegentien van"
    }
   ],
   "target": {
    "id": "https://data.goldenagents.org/datasets/dh2020/canvas/A16098000171",
    "selector": {
     "type": "SvgSelector",
     "value": "<svg xmlns=\"http://www.w3.org/2000/svg\"><path fill-rule=\"evenodd\" fill=\"#66cc99\" stroke=\"#555555\" stroke-width=\"1\" fill-opacity=\"0.08\" d=\"M 1066,692 L 1122,692 L 1179,692 L 1235,692 L 1292,694 L 1348,696 L 1405,696 L 1461,698 L 1518,700 L 1574,702 L 1631,704 L 1687,707 L 1744,710 L 1800,712 L 1857,714 L 1913,716 L 1970,719 L 2026,722 L 2083,722 L 2139,724 L 2196,726 L 2196,678 L 2139,676 L 2083,674 L 2026,674 L 1970,671 L 1913,668 L 1857,666 L 1800,664 L 1744,662 L 1687,659 L 1631,656 L 1574,654 L 1518,652 L 1461,650 L 1405,648 L 1348,648 L 1292,646 L 1235,644 L 1179,644 L 1122,644 L 1066,644 L 1066,692 Z\"/></svg>"
    }
   }
  },
  {
   "@context": "http://iiif.io/api/presentation/3/context.json",
   "id": "https://data.goldenagents.org/datasets/dh2020/annotation/A16098000171/r2l7",
   "type": "Annotation",
   "motivation": "supplementing",
   "body": [
    {
     "type": "TextualBody",
     "language": "nl",
     "value": "vijff ellen"
    }
   ],
   "target": {
    "id": "https://data.goldenagents.org/datasets/dh2020/canvas/A16098000171",
    "selector": {
     "type": "SvgSelector",
     "value": "<svg xmlns=\"http://www.w3.org/2000/svg\"><path fill-rule=\"evenodd\" fill=\"#66cc99\" stroke=\"#555555\" stroke-width=\"1\" fill-opacity=\"0.08\" d=\"M 1088,758 L 1113,760 L 1139,762 L 1165,764 L 1190,765 L 1216,766 L 1242,767 L 1268,768 L 1293,768 L 1319,768 L 1345,768 L 1371,770 L 1396,771 L 1422,773 L 1448,774 L 1474,776 L 1474,728 L 1448,726 L 1422,725 L 1396,723 L 1371,722 L 1345,720 L 1319,720 L 1293,720 L 1268,720 L 1242,719 L 1216,718 L 1190,717 L 1165,716 L 1139,714 L 1113,712 L 1088,710 L 1088,758 Z\"/></svg>"
    }
   }
  },
  {
   "@context": "http://iiif.io/api/presentation/3/context.json",
   "id": "https://data.goldenagents.org/datasets/dh2020/annotation/A16098000171/r2l8",
   "type": "Annotation",
   "motivation": "supplementing",
   "body": [
    {
     "type": "TextualBody",
     "language": "nl",
     "value": "Acht kleijne peuluw-lakens,"
    }
   ],
   "target": {
    "id": "https://data.goldenagents.org/datasets/dh2020/canvas/A16098000171",
    "selector": {
     "type": "SvgSelector",
     "value": "<svg xmlns=\"http://www.w3.org/2000/svg\"><path fill-rule=\"evenodd\" fill=\"#66cc99\" stroke=\"#555555\" stroke-width=\"1\" fill-opacity=\"0.08\" d=\"M 868,864 L 924,863 L 981,862 L 1037,862 L 1094,862 L 1151,862 L 1207,862 L 1264,862 L 1320,864 L 1377,864 L 1434,866 L 1490,866 L 1547,868 L 1603,870 L 1660,873 L 1717,876 L 1773,878 L 1830,882 L 1886,886 L 1943,889 L 2000,894 L 2000,846 L 1943,841 L 1886,838 L 1830,834 L 1773,830 L 1717,828 L 1660,825 L 1603,822 L 1547,820 L 1490,818 L 1434,818 L 1377,816 L 1320,816 L 1264,814 L 1207,814 L 1151,814 L 1094,814 L 1037,814 L 981,814 L 924,815 L 868,816 L 868,864 Z\"/></svg>"
    }
   }
  },
  {
   "@context": "http://iiif.io/api/presentation/3/context.json",
   "id": "https://data.goldenagents.org/datasets/dh2020/annotation/A16098000171/r2l9",
   "type": "Annotation",
   "motivation": "supplementing",
   "body": [
    {
     "type": "TextualBody",
     "language": "nl",
     "value": "nogh drij grote peuluw lakens,"
    }
   ],
   "target": {
    "id": "https://data.goldenagents.org/datasets/dh2020/canvas/A16098000171",
    "selector": {
     "type": "SvgSelector",
     "value": "<svg xmlns=\"http://www.w3.org/2000/svg\"><path fill-rule=\"evenodd\" fill=\"#66cc99\" stroke=\"#555555\" stroke-width=\"1\" fill-opacity=\"0.08\" d=\"M 888,962 L 946,962 L 1004,962 L 1063,964 L 1121,964 L 1180,964 L 1238,964 L 1296,964 L 1355,964 L 1413,964 L 1472,964 L 1530,966 L 1588,966 L 1647,967 L 1705,968 L 1764,968 L 1822,970 L 1880,972 L 1939,974 L 1997,976 L 2056,978 L 2056,930 L 1997,928 L 1939,926 L 1880,924 L 1822,922 L 1764,920 L 1705,920 L 1647,919 L 1588,918 L 1530,918 L 1472,916 L 1413,916 L 1355,916 L 1296,916 L 1238,916 L 1180,916 L 1121,916 L 1063,916 L 1004,914 L 946,914 L 888,914 L 888,962 Z\"/></svg>"
    }
   }
  },
  {
   "@context": "http://iiif.io/api/presentation/3/context.json",
   "id": "https://data.goldenagents.org/datasets/dh2020/annotation/A16098000171/r2l10",
   "type": "Annotation",
   "motivation": "supplementing",
   "body": [
    {
     "type": "TextualBody",
     "language": "nl",
     "value": "Twee grote slopen"
    }
   ],
   "target": {
    "id": "https://data.goldenagents.org/datasets/dh2020/canvas/A16098000171",
    "selector": {
     "type": "SvgSelector",
     "value": "<svg xmlns=\"http://www.w3.org/2000/svg\"><path fill-rule=\"evenodd\" fill=\"#66cc99\" stroke=\"#555555\" stroke-width=\"1\" fill-opacity=\"0.08\" d=\"M 894,1056 L 932,1054 L 970,1053 L 1008,1052 L 1046,1052 L 1085,1051 L 1123,1050 L 1161,1050 L 1199,1050 L 1237,1050 L 1276,1050 L 1314,1050 L 1352,1050 L 1390,1050 L 1428,1050 L 1467,1050 L 1505,1051 L 1543,1052 L 1581,1052 L 1619,1052 L 1658,1052 L 1658,1004 L 1619,1004 L 1581,1004 L 1543,1004 L 1505,1003 L 1467,1002 L 1428,1002 L 1390,1002 L 1352,1002 L 1314,1002 L 1276,1002 L 1237,1002 L 1199,1002 L 1161,1002 L 1123,1002 L 1085,1003 L 1046,1004 L 1008,1004 L 970,1005 L 932,1006 L 894,1008 L 894,1056 Z\"/></svg>"
    }
   }
  },
  {
   "@context": "http://iiif.io/api/presentation/3/context.json",
   "id": "https://data.goldenagents.org/datasets/dh2020/annotation/A16098000171/r2l11",
   "type": "Annotation",
   "motivation": "supplementing",
   "body": [
    {
     "type": "TextualBody",
     "language": "nl",
     "value": "Seventien paar slopen"
    }
   ],
   "target": {
    "id": "https://data.goldenagents.org/datasets/dh2020/canvas/A16098000171",
    "selector": {
     "type": "SvgSelector",
     "value": "<svg xmlns=\"http://www.w3.org/2000/svg\"><path fill-rule=\"evenodd\" fill=\"#66cc99\" stroke=\"#555555\" stroke-width=\"1\" fill-opacity=\"0.08\" d=\"M 894,1138 L 932,1138 L 970,1138 L 1009,1138 L 1047,1136 L 1086,1136 L 1124,1136 L 1162,1137 L 1201,1138 L 1239,1138 L 1278,1138 L 1316,1138 L 1354,1138 L 1393,1138 L 1431,1140 L 1470,1140 L 1508,1140 L 1546,1140 L 1585,1140 L 1623,1140 L 1662,1140 L 1662,1092 L 1623,1092 L 1585,1092 L 1546,1092 L 1508,1092 L 1470,1092 L 1431,1092 L 1393,1090 L 1354,1090 L 1316,1090 L 1278,1090 L 1239,1090 L 1201,1090 L 1162,1089 L 1124,1088 L 1086,1088 L 1047,1088 L 1009,1090 L 970,1090 L 932,1090 L 894,1090 L 894,1138 Z\"/></svg>"
    }
   }
  },
  {
   "@context": "http://iiif.io/api/presentation/3/context.json",
   "id": "https://data.goldenagents.org/datasets/dh2020/annotation/A16098000171/r2l12",
   "type": "Annotation",
   "motivation": "supplementing",
   "body": [
    {
     "type": "TextualBody",
     "language": "nl",
     "value": "seste"
    }
   ],
   "target": {
    "id": "https://data.goldenagents.org/datasets/dh2020/canvas/A16098000171",
    "selector": {
     "type": "SvgSelector",
     "value": "<svg xmlns=\"http://www.w3.org/2000/svg\"><path fill-rule=\"evenodd\" fill=\"#66cc99\" stroke=\"#555555\" stroke-width=\"1\" fill-opacity=\"0.08\" d=\"M 898,1219 L 924,1217 L 951,1214 L 978,1213 L 1005,1213 L 1032,1215 L 1058,1215 L 1085,1217 L 1112,1217 L 1139,1217 L 1166,1215 L 1166,1175 L 1139,1177 L 1112,1177 L 1085,1177 L 1058,1175 L 1032,1175 L 1005,1173 L 978,1173 L 951,1174 L 924,1177 L 898,1179 L 898,1219 Z\"/></svg>"
    }
   }
  },
  {
   "@context": "http://iiif.io/api/presentation/3/context.json",
   "id": "https://data.goldenagents.org/datasets/dh2020/annotation/A16098000171/r2l13",
   "type": "Annotation",
   "motivation": "supplementing",
   "body": [
    {
     "type": "TextualBody",
     "language": "nl",
     "value": "Sestien kleijne slopen,"
    }
   ],
   "target": {
    "id": "https://data.goldenagents.org/datasets/dh2020/canvas/A16098000171",
    "selector": {
     "type": "SvgSelector",
     "value": "<svg xmlns=\"http://www.w3.org/2000/svg\"><path fill-rule=\"evenodd\" fill=\"#66cc99\" stroke=\"#555555\" stroke-width=\"1\" fill-opacity=\"0.08\" d=\"M 906,1281 L 942,1279 L 979,1278 L 1015,1277 L 1052,1275 L 1089,1274 L 1125,1273 L 1162,1271 L 1198,1271 L 1235,1269 L 1272,1269 L 1308,1269 L 1345,1269 L 1381,1269 L 1418,1269 L 1455,1269 L 1491,1270 L 1528,1271 L 1564,1272 L 1601,1273 L 1638,1275 L 1638,1235 L 1601,1233 L 1564,1232 L 1528,1231 L 1491,1230 L 1455,1229 L 1418,1229 L 1381,1229 L 1345,1229 L 1308,1229 L 1272,1229 L 1235,1229 L 1198,1231 L 1162,1231 L 1125,1233 L 1089,1234 L 1052,1235 L 1015,1237 L 979,1238 L 942,1239 L 906,1241 L 906,1281 Z\"/></svg>"
    }
   }
  },
  {
   "@context": "http://iiif.io/api/presentation/3/context.json",
   "id": "https://data.goldenagents.org/datasets/dh2020/annotation/A16098000171/r2l14",
   "type": "Annotation",
   "motivation": "supplementing",
   "body": [
    {
     "type": "TextualBody",
     "language": "nl",
     "value": "Twee ongemaakte Kottoene slopen"
    }
   ],
   "target": {
    "id": "https://data.goldenagents.org/datasets/dh2020/canvas/A16098000171",
    "selector": {
     "type": "SvgSelector",
     "value": "<svg xmlns=\"http://www.w3.org/2000/svg\"><path fill-rule=\"evenodd\" fill=\"#66cc99\" stroke=\"#555555\" stroke-width=\"1\" fill-opacity=\"0.08\" d=\"M 928,1350 L 990,1350 L 1053,1348 L 1115,1348 L 1178,1346 L 1241,1346 L 1303,1346 L 1366,1344 L 1428,1344 L 1491,1344 L 1554,1344 L 1616,1346 L 1679,1346 L 1741,1346 L 1804,1348 L 1867,1349 L 1929,1350 L 1992,1352 L 2054,1354 L 2117,1356 L 2180,1358 L 2180,1310 L 2117,1308 L 2054,1306 L 1992,1304 L 1929,1302 L 1867,1301 L 1804,1300 L 1741,1298 L 1679,1298 L 1616,1298 L 1554,1296 L 1491,1296 L 1428,1296 L 1366,1296 L 1303,1298 L 1241,1298 L 1178,1298 L 1115,1300 L 1053,1300 L 990,1302 L 928,1302 L 928,1350 Z\"/></svg>"
    }
   }
  },
  {
   "@context": "http://iiif.io/api/presentation/3/context.json",
   "id": "https://data.goldenagents.org/datasets/dh2020/annotation/A16098000171/r2l15",
   "type": "Annotation",
   "motivation": "supplementing",
   "body": [
    {
     "type": "TextualBody",
     "language": "nl",
     "value": "Acht kottoene luijers,"
    }
   ],
   "target": {
    "id": "https://data.goldenagents.org/datasets/dh2020/canvas/A16098000171",
    "selector": {
     "type": "SvgSelector",
     "value": "<svg xmlns=\"http://www.w3.org/2000/svg\"><path fill-rule=\"evenodd\" fill=\"#66cc99\" stroke=\"#555555\" stroke-width=\"1\" fill-opacity=\"0.08\" d=\"M 878,1436 L 917,1434 L 956,1432 L 996,1428 L 1035,1426 L 1075,1424 L 1114,1423 L 1153,1421 L 1193,1420 L 1232,1420 L 1272,1419 L 1311,1418 L 1350,1418 L 1390,1418 L 1429,1418 L 1469,1418 L 1508,1418 L 1547,1418 L 1587,1418 L 1626,1418 L 1666,1418 L 1666,1370 L 1626,1370 L 1587,1370 L 1547,1370 L 1508,1370 L 1469,1370 L 1429,1370 L 1390,1370 L 1350,1370 L 1311,1370 L 1272,1371 L 1232,1372 L 1193,1372 L 1153,1373 L 1114,1375 L 1075,1376 L 1035,1378 L 996,1380 L 956,1384 L 917,1386 L 878,1388 L 878,1436 Z\"/></svg>"
    }
   }
  },
  {
   "@context": "http://iiif.io/api/presentation/3/context.json",
   "id": "https://data.goldenagents.org/datasets/dh2020/annotation/A16098000171/r2l16",
   "type": "Annotation",
   "motivation": "supplementing",
   "body": [
    {
     "type": "TextualBody",
     "language": "nl",
     "value": "Twee langhwerpige kottoene"
    }
   ],
   "target": {
    "id": "https://data.goldenagents.org/datasets/dh2020/canvas/A16098000171",
    "selector": {
     "type": "SvgSelector",
     "value": "<svg xmlns=\"http://www.w3.org/2000/svg\"><path fill-rule=\"evenodd\" fill=\"#66cc99\" stroke=\"#555555\" stroke-width=\"1\" fill-opacity=\"0.08\" d=\"M 932,1518 L 991,1513 L 1050,1510 L 1109,1508 L 1168,1505 L 1227,1504 L 1286,1504 L 1345,1504 L 1404,1504 L 1463,1504 L 1523,1506 L 1582,1506 L 1641,1507 L 1700,1508 L 1759,1509 L 1818,1510 L 1877,1510 L 1936,1510 L 1995,1510 L 2054,1510 L 2114,1508 L 2114,1460 L 2054,1462 L 1995,1462 L 1936,1462 L 1877,1462 L 1818,1462 L 1759,1461 L 1700,1460 L 1641,1459 L 1582,1458 L 1523,1458 L 1463,1456 L 1404,1456 L 1345,1456 L 1286,1456 L 1227,1456 L 1168,1457 L 1109,1460 L 1050,1462 L 991,1465 L 932,1470 L 932,1518 Z\"/></svg>"
    }
   }
  },
  {
   "@context": "http://iiif.io/api/presentation/3/context.json",
   "id": "https://data.goldenagents.org/datasets/dh2020/annotation/A16098000171/r2l17",
   "type": "Annotation",
   "motivation": "supplementing",
   "body": [
    {
     "type": "TextualBody",
     "language": "nl",
     "value": "doeckjes"
    }
   ],
   "target": {
    "id": "https://data.goldenagents.org/datasets/dh2020/canvas/A16098000171",
    "selector": {
     "type": "SvgSelector",
     "value": "<svg xmlns=\"http://www.w3.org/2000/svg\"><path fill-rule=\"evenodd\" fill=\"#66cc99\" stroke=\"#555555\" stroke-width=\"1\" fill-opacity=\"0.08\" d=\"M 1074,1576 L 1101,1574 L 1128,1573 L 1155,1572 L 1182,1573 L 1209,1574 L 1236,1574 L 1263,1576 L 1290,1576 L 1317,1576 L 1344,1574 L 1344,1526 L 1317,1528 L 1290,1528 L 1263,1528 L 1236,1526 L 1209,1526 L 1182,1525 L 1155,1524 L 1128,1525 L 1101,1526 L 1074,1528 L 1074,1576 Z\"/></svg>"
    }
   }
  },
  {
   "@context": "http://iiif.io/api/presentation/3/context.json",
   "id": "https://data.goldenagents.org/datasets/dh2020/annotation/A16098000171/r2l18",
   "type": "Annotation",
   "motivation": "supplementing",
   "body": [
    {
     "type": "TextualBody",
     "language": "nl",
     "value": "Ses kottoene Neusdoecken met roo"
    }
   ],
   "target": {
    "id": "https://data.goldenagents.org/datasets/dh2020/canvas/A16098000171",
    "selector": {
     "type": "SvgSelector",
     "value": "<svg xmlns=\"http://www.w3.org/2000/svg\"><path fill-rule=\"evenodd\" fill=\"#66cc99\" stroke=\"#555555\" stroke-width=\"1\" fill-opacity=\"0.08\" d=\"M 874,1648 L 934,1647 L 994,1646 L 1054,1646 L 1114,1646 L 1175,1646 L 1235,1646 L 1295,1646 L 1355,1648 L 1415,1648 L 1476,1650 L 1536,1652 L 1596,1654 L 1656,1656 L 1716,1658 L 1777,1660 L 1837,1662 L 1897,1664 L 1957,1667 L 2017,1670 L 2078,1672 L 2078,1630 L 2017,1628 L 1957,1625 L 1897,1622 L 1837,1620 L 1777,1618 L 1716,1616 L 1656,1614 L 1596,1612 L 1536,1610 L 1476,1608 L 1415,1606 L 1355,1606 L 1295,1604 L 1235,1604 L 1175,1604 L 1114,1604 L 1054,1604 L 994,1604 L 934,1605 L 874,1606 L 874,1648 Z\"/></svg>"
    }
   }
  },
  {
   "@context": "http://iiif.io/api/presentation/3/context.json",
   "id": "https://data.goldenagents.org/datasets/dh2020/annotation/A16098000171/r2l19",
   "type": "Annotation",
   "motivation": "supplementing",
   "body": [
    {
     "type": "TextualBody",
     "language": "nl",
     "value": "streepjes"
    }
   ],
   "target": {
    "id": "https://data.goldenagents.org/datasets/dh2020/canvas/A16098000171",
    "selector": {
     "type": "SvgSelector",
     "value": "<svg xmlns=\"http://www.w3.org/2000/svg\"><path fill-rule=\"evenodd\" fill=\"#66cc99\" stroke=\"#555555\" stroke-width=\"1\" fill-opacity=\"0.08\" d=\"M 1120,1704 L 1146,1702 L 1172,1703 L 1199,1704 L 1225,1705 L 1252,1706 L 1278,1707 L 1305,1709 L 1331,1712 L 1358,1712 L 1384,1714 L 1411,1714 L 1437,1716 L 1464,1714 L 1464,1672 L 1437,1674 L 1411,1672 L 1384,1672 L 1358,1670 L 1331,1670 L 1305,1667 L 1278,1665 L 1252,1664 L 1225,1663 L 1199,1662 L 1172,1661 L 1146,1660 L 1120,1662 L 1120,1704 Z\"/></svg>"
    }
   }
  },
  {
   "@context": "http://iiif.io/api/presentation/3/context.json",
   "id": "https://data.goldenagents.org/datasets/dh2020/annotation/A16098000171/r2l20",
   "type": "Annotation",
   "motivation": "supplementing",
   "body": [
    {
     "type": "TextualBody",
     "language": "nl",
     "value": "Tww kottoene dwalen"
    }
   ],
   "target": {
    "id": "https://data.goldenagents.org/datasets/dh2020/canvas/A16098000171",
    "selector": {
     "type": "SvgSelector",
     "value": "<svg xmlns=\"http://www.w3.org/2000/svg\"><path fill-rule=\"evenodd\" fill=\"#66cc99\" stroke=\"#555555\" stroke-width=\"1\" fill-opacity=\"0.08\" d=\"M 896,1804 L 945,1801 L 995,1798 L 1044,1796 L 1094,1796 L 1144,1796 L 1193,1794 L 1243,1795 L 1292,1796 L 1342,1796 L 1392,1796 L 1441,1798 L 1491,1798 L 1540,1800 L 1590,1800 L 1640,1801 L 1689,1802 L 1739,1802 L 1788,1802 L 1838,1802 L 1888,1802 L 1888,1754 L 1838,1754 L 1788,1754 L 1739,1754 L 1689,1754 L 1640,1753 L 1590,1752 L 1540,1752 L 1491,1750 L 1441,1750 L 1392,1748 L 1342,1748 L 1292,1748 L 1243,1747 L 1193,1746 L 1144,1748 L 1094,1748 L 1044,1748 L 995,1750 L 945,1753 L 896,1756 L 896,1804 Z\"/></svg>"
    }
   }
  },
  {
   "@context": "http://iiif.io/api/presentation/3/context.json",
   "id": "https://data.goldenagents.org/datasets/dh2020/annotation/A16098000171/r2l21",
   "type": "Annotation",
   "motivation": "supplementing",
   "body": [
    {
     "type": "TextualBody",
     "language": "nl",
     "value": "ses kottoene schoorsteenkleetjes"
    }
   ],
   "target": {
    "id": "https://data.goldenagents.org/datasets/dh2020/canvas/A16098000171",
    "selector": {
     "type": "SvgSelector",
     "value": "<svg xmlns=\"http://www.w3.org/2000/svg\"><path fill-rule=\"evenodd\" fill=\"#66cc99\" stroke=\"#555555\" stroke-width=\"1\" fill-opacity=\"0.08\" d=\"M 776,1892 L 845,1890 L 914,1888 L 983,1886 L 1052,1884 L 1121,1884 L 1190,1884 L 1259,1882 L 1328,1884 L 1397,1884 L 1466,1884 L 1535,1886 L 1604,1887 L 1673,1888 L 1742,1890 L 1811,1892 L 1880,1894 L 1949,1895 L 2018,1898 L 2087,1899 L 2156,1902 L 2156,1854 L 2087,1851 L 2018,1850 L 1949,1847 L 1880,1846 L 1811,1844 L 1742,1842 L 1673,1840 L 1604,1839 L 1535,1838 L 1466,1836 L 1397,1836 L 1328,1836 L 1259,1834 L 1190,1836 L 1121,1836 L 1052,1836 L 983,1838 L 914,1840 L 845,1842 L 776,1844 L 776,1892 Z\"/></svg>"
    }
   }
  },
  {
   "@context": "http://iiif.io/api/presentation/3/context.json",
   "id": "https://data.goldenagents.org/datasets/dh2020/annotation/A16098000171/r2l22",
   "type": "Annotation",
   "motivation": "supplementing",
   "body": [
    {
     "type": "TextualBody",
     "language": "nl",
     "value": "Dertigh linne neusdoecken,"
    }
   ],
   "target": {
    "id": "https://data.goldenagents.org/datasets/dh2020/canvas/A16098000171",
    "selector": {
     "type": "SvgSelector",
     "value": "<svg xmlns=\"http://www.w3.org/2000/svg\"><path fill-rule=\"evenodd\" fill=\"#66cc99\" stroke=\"#555555\" stroke-width=\"1\" fill-opacity=\"0.08\" d=\"M 896,1966 L 949,1967 L 1002,1968 L 1055,1970 L 1108,1970 L 1161,1972 L 1214,1972 L 1267,1972 L 1320,1972 L 1373,1972 L 1426,1974 L 1479,1974 L 1532,1975 L 1585,1976 L 1638,1978 L 1691,1980 L 1744,1982 L 1797,1984 L 1850,1988 L 1903,1993 L 1956,1998 L 1956,1950 L 1903,1945 L 1850,1940 L 1797,1936 L 1744,1934 L 1691,1932 L 1638,1930 L 1585,1928 L 1532,1927 L 1479,1926 L 1426,1926 L 1373,1924 L 1320,1924 L 1267,1924 L 1214,1924 L 1161,1924 L 1108,1922 L 1055,1922 L 1002,1920 L 949,1919 L 896,1918 L 896,1966 Z\"/></svg>"
    }
   }
  },
  {
   "@context": "http://iiif.io/api/presentation/3/context.json",
   "id": "https://data.goldenagents.org/datasets/dh2020/annotation/A16098000171/r2l23",
   "type": "Annotation",
   "motivation": "supplementing",
   "body": [
    {
     "type": "TextualBody",
     "language": "nl",
     "value": "Twee dosijn Sarvietten pavij"
    }
   ],
   "target": {
    "id": "https://data.goldenagents.org/datasets/dh2020/canvas/A16098000171",
    "selector": {
     "type": "SvgSelector",
     "value": "<svg xmlns=\"http://www.w3.org/2000/svg\"><path fill-rule=\"evenodd\" fill=\"#66cc99\" stroke=\"#555555\" stroke-width=\"1\" fill-opacity=\"0.08\" d=\"M 888,2046 L 939,2050 L 991,2052 L 1043,2054 L 1095,2056 L 1147,2056 L 1199,2056 L 1251,2056 L 1303,2056 L 1355,2056 L 1407,2056 L 1458,2056 L 1510,2056 L 1562,2056 L 1614,2056 L 1666,2058 L 1718,2062 L 1770,2064 L 1822,2068 L 1874,2073 L 1926,2080 L 1926,2032 L 1874,2025 L 1822,2020 L 1770,2016 L 1718,2014 L 1666,2010 L 1614,2008 L 1562,2008 L 1510,2008 L 1458,2008 L 1407,2008 L 1355,2008 L 1303,2008 L 1251,2008 L 1199,2008 L 1147,2008 L 1095,2008 L 1043,2006 L 991,2004 L 939,2002 L 888,1998 L 888,2046 Z\"/></svg>"
    }
   }
  },
  {
   "@context": "http://iiif.io/api/presentation/3/context.json",
   "id": "https://data.goldenagents.org/datasets/dh2020/annotation/A16098000171/r2l24",
   "type": "Annotation",
   "motivation": "supplementing",
   "body": [
    {
     "type": "TextualBody",
     "language": "nl",
     "value": "Nogh"
    }
   ],
   "target": {
    "id": "https://data.goldenagents.org/datasets/dh2020/canvas/A16098000171",
    "selector": {
     "type": "SvgSelector",
     "value": "<svg xmlns=\"http://www.w3.org/2000/svg\"><path fill-rule=\"evenodd\" fill=\"#66cc99\" stroke=\"#555555\" stroke-width=\"1\" fill-opacity=\"0.08\" d=\"M 656,2122 L 682,2120 L 709,2118 L 735,2118 L 762,2118 L 788,2120 L 815,2121 L 842,2124 L 842,2076 L 815,2073 L 788,2072 L 762,2070 L 735,2070 L 709,2070 L 682,2072 L 656,2074 L 656,2122 Z\"/></svg>"
    }
   }
  },
  {
   "@context": "http://iiif.io/api/presentation/3/context.json",
   "id": "https://data.goldenagents.org/datasets/dh2020/annotation/A16098000171/r2l25",
   "type": "Annotation",
   "motivation": "supplementing",
   "body": [
    {
     "type": "TextualBody",
     "language": "nl",
     "value": "Twee grote Sarvietten pavij"
    }
   ],
   "target": {
    "id": "https://data.goldenagents.org/datasets/dh2020/canvas/A16098000171",
    "selector": {
     "type": "SvgSelector",
     "value": "<svg xmlns=\"http://www.w3.org/2000/svg\"><path fill-rule=\"evenodd\" fill=\"#66cc99\" stroke=\"#555555\" stroke-width=\"1\" fill-opacity=\"0.08\" d=\"M 900,2112 L 952,2117 L 1004,2121 L 1056,2123 L 1109,2126 L 1161,2127 L 1213,2128 L 1266,2130 L 1318,2130 L 1370,2130 L 1423,2130 L 1475,2130 L 1527,2131 L 1579,2132 L 1632,2132 L 1684,2134 L 1736,2135 L 1789,2138 L 1841,2140 L 1893,2145 L 1946,2150 L 1946,2102 L 1893,2097 L 1841,2092 L 1789,2090 L 1736,2087 L 1684,2086 L 1632,2084 L 1579,2084 L 1527,2083 L 1475,2082 L 1423,2082 L 1370,2082 L 1318,2082 L 1266,2082 L 1213,2080 L 1161,2079 L 1109,2078 L 1056,2075 L 1004,2073 L 952,2069 L 900,2064 L 900,2112 Z\"/></svg>"
    }
   }
  },
  {
   "@context": "http://iiif.io/api/presentation/3/context.json",
   "id": "https://data.goldenagents.org/datasets/dh2020/annotation/A16098000171/r2l26",
   "type": "Annotation",
   "motivation": "supplementing",
   "body": [
    {
     "type": "TextualBody",
     "language": "nl",
     "value": "Twee dosijn Sarvietten lavender met"
    }
   ],
   "target": {
    "id": "https://data.goldenagents.org/datasets/dh2020/canvas/A16098000171",
    "selector": {
     "type": "SvgSelector",
     "value": "<svg xmlns=\"http://www.w3.org/2000/svg\"><path fill-rule=\"evenodd\" fill=\"#66cc99\" stroke=\"#555555\" stroke-width=\"1\" fill-opacity=\"0.08\" d=\"M 900,2196 L 961,2198 L 1023,2198 L 1085,2200 L 1147,2201 L 1209,2202 L 1270,2205 L 1332,2206 L 1394,2208 L 1456,2210 L 1518,2212 L 1579,2213 L 1641,2215 L 1703,2216 L 1765,2218 L 1827,2218 L 1888,2220 L 1950,2220 L 2012,2220 L 2074,2220 L 2136,2220 L 2136,2172 L 2074,2172 L 2012,2172 L 1950,2172 L 1888,2172 L 1827,2170 L 1765,2170 L 1703,2168 L 1641,2167 L 1579,2165 L 1518,2164 L 1456,2162 L 1394,2160 L 1332,2158 L 1270,2157 L 1209,2154 L 1147,2153 L 1085,2152 L 1023,2150 L 961,2150 L 900,2148 L 900,2196 Z\"/></svg>"
    }
   }
  },
  {
   "@context": "http://iiif.io/api/presentation/3/context.json",
   "id": "https://data.goldenagents.org/datasets/dh2020/annotation/A16098000171/r2l27",
   "type": "Annotation",
   "motivation": "supplementing",
   "body": [
    {
     "type": "TextualBody",
     "language": "nl",
     "value": "twee schuijnttjes,"
    }
   ],
   "target": {
    "id": "https://data.goldenagents.org/datasets/dh2020/canvas/A16098000171",
    "selector": {
     "type": "SvgSelector",
     "value": "<svg xmlns=\"http://www.w3.org/2000/svg\"><path fill-rule=\"evenodd\" fill=\"#66cc99\" stroke=\"#555555\" stroke-width=\"1\" fill-opacity=\"0.08\" d=\"M 1064,2262 L 1094,2263 L 1125,2264 L 1156,2264 L 1187,2266 L 1218,2267 L 1249,2268 L 1280,2268 L 1311,2270 L 1342,2270 L 1373,2272 L 1403,2273 L 1434,2274 L 1465,2275 L 1496,2276 L 1527,2277 L 1558,2278 L 1589,2280 L 1620,2280 L 1651,2282 L 1682,2284 L 1682,2236 L 1651,2234 L 1620,2232 L 1589,2232 L 1558,2230 L 1527,2229 L 1496,2228 L 1465,2227 L 1434,2226 L 1403,2225 L 1373,2224 L 1342,2222 L 1311,2222 L 1280,2220 L 1249,2220 L 1218,2219 L 1187,2218 L 1156,2216 L 1125,2216 L 1094,2215 L 1064,2214 L 1064,2262 Z\"/></svg>"
    }
   }
  },
  {
   "@context": "http://iiif.io/api/presentation/3/context.json",
   "id": "https://data.goldenagents.org/datasets/dh2020/annotation/A16098000171/r2l28",
   "type": "Annotation",
   "motivation": "supplementing",
   "body": [
    {
     "type": "TextualBody",
     "language": "nl",
     "value": "Achtien Sarvietten gekepert lavendel"
    }
   ],
   "target": {
    "id": "https://data.goldenagents.org/datasets/dh2020/canvas/A16098000171",
    "selector": {
     "type": "SvgSelector",
     "value": "<svg xmlns=\"http://www.w3.org/2000/svg\"><path fill-rule=\"evenodd\" fill=\"#66cc99\" stroke=\"#555555\" stroke-width=\"1\" fill-opacity=\"0.08\" d=\"M 864,2334 L 926,2336 L 989,2340 L 1051,2340 L 1114,2342 L 1176,2344 L 1239,2344 L 1301,2344 L 1364,2346 L 1426,2346 L 1489,2346 L 1551,2346 L 1614,2346 L 1676,2348 L 1739,2348 L 1801,2350 L 1864,2350 L 1926,2352 L 1989,2354 L 2051,2358 L 2114,2360 L 2114,2312 L 2051,2310 L 1989,2306 L 1926,2304 L 1864,2302 L 1801,2302 L 1739,2300 L 1676,2300 L 1614,2298 L 1551,2298 L 1489,2298 L 1426,2298 L 1364,2298 L 1301,2296 L 1239,2296 L 1176,2296 L 1114,2294 L 1051,2292 L 989,2292 L 926,2288 L 864,2286 L 864,2334 Z\"/></svg>"
    }
   }
  },
  {
   "@context": "http://iiif.io/api/presentation/3/context.json",
   "id": "https://data.goldenagents.org/datasets/dh2020/annotation/A16098000171/r2l29",
   "type": "Annotation",
   "motivation": "supplementing",
   "body": [
    {
     "type": "TextualBody",
     "language": "nl",
     "value": "Ses sarvietten uijters beeltenis"
    }
   ],
   "target": {
    "id": "https://data.goldenagents.org/datasets/dh2020/canvas/A16098000171",
    "selector": {
     "type": "SvgSelector",
     "value": "<svg xmlns=\"http://www.w3.org/2000/svg\"><path fill-rule=\"evenodd\" fill=\"#66cc99\" stroke=\"#555555\" stroke-width=\"1\" fill-opacity=\"0.08\" d=\"M 888,2428 L 945,2428 L 1002,2430 L 1059,2430 L 1116,2430 L 1173,2430 L 1230,2428 L 1287,2428 L 1344,2428 L 1401,2428 L 1459,2428 L 1516,2428 L 1573,2428 L 1630,2430 L 1687,2431 L 1744,2434 L 1801,2437 L 1858,2441 L 1915,2447 L 1972,2453 L 2030,2460 L 2030,2412 L 1972,2405 L 1915,2399 L 1858,2393 L 1801,2389 L 1744,2386 L 1687,2383 L 1630,2382 L 1573,2380 L 1516,2380 L 1459,2380 L 1401,2380 L 1344,2380 L 1287,2380 L 1230,2380 L 1173,2382 L 1116,2382 L 1059,2382 L 1002,2382 L 945,2380 L 888,2380 L 888,2428 Z\"/></svg>"
    }
   }
  },
  {
   "@context": "http://iiif.io/api/presentation/3/context.json",
   "id": "https://data.goldenagents.org/datasets/dh2020/annotation/A16098000171/r2l30",
   "type": "Annotation",
   "motivation": "supplementing",
   "body": [
    {
     "type": "TextualBody",
     "language": "nl",
     "value": "Tien sarvietten lavender met"
    }
   ],
   "target": {
    "id": "https://data.goldenagents.org/datasets/dh2020/canvas/A16098000171",
    "selector": {
     "type": "SvgSelector",
     "value": "<svg xmlns=\"http://www.w3.org/2000/svg\"><path fill-rule=\"evenodd\" fill=\"#66cc99\" stroke=\"#555555\" stroke-width=\"1\" fill-opacity=\"0.08\" d=\"M 914,2499 L 965,2501 L 1017,2501 L 1069,2501 L 1121,2499 L 1173,2499 L 1225,2499 L 1277,2499 L 1329,2499 L 1381,2498 L 1433,2497 L 1484,2497 L 1536,2497 L 1588,2499 L 1640,2499 L 1692,2499 L 1744,2501 L 1796,2503 L 1848,2504 L 1900,2506 L 1952,2509 L 1952,2464 L 1900,2461 L 1848,2459 L 1796,2458 L 1744,2456 L 1692,2454 L 1640,2454 L 1588,2454 L 1536,2452 L 1484,2452 L 1433,2452 L 1381,2453 L 1329,2454 L 1277,2454 L 1225,2454 L 1173,2454 L 1121,2454 L 1069,2456 L 1017,2456 L 965,2456 L 914,2454 L 914,2499 Z\"/></svg>"
    }
   }
  },
  {
   "@context": "http://iiif.io/api/presentation/3/context.json",
   "id": "https://data.goldenagents.org/datasets/dh2020/annotation/A16098000171/r2l31",
   "type": "Annotation",
   "motivation": "supplementing",
   "body": [
    {
     "type": "TextualBody",
     "language": "nl",
     "value": "rosen"
    }
   ],
   "target": {
    "id": "https://data.goldenagents.org/datasets/dh2020/canvas/A16098000171",
    "selector": {
     "type": "SvgSelector",
     "value": "<svg xmlns=\"http://www.w3.org/2000/svg\"><path fill-rule=\"evenodd\" fill=\"#66cc99\" stroke=\"#555555\" stroke-width=\"1\" fill-opacity=\"0.08\" d=\"M 1140,2555 L 1166,2559 L 1192,2559 L 1218,2559 L 1244,2558 L 1270,2557 L 1296,2555 L 1296,2515 L 1270,2517 L 1244,2518 L 1218,2519 L 1192,2519 L 1166,2519 L 1140,2515 L 1140,2555 Z\"/></svg>"
    }
   }
  },
  {
   "@context": "http://iiif.io/api/presentation/3/context.json",
   "id": "https://data.goldenagents.org/datasets/dh2020/annotation/A16098000171/r2l32",
   "type": "Annotation",
   "motivation": "supplementing",
   "body": [
    {
     "type": "TextualBody",
     "language": "nl",
     "value": "Seven sarvietten lavender van Beste"
    }
   ],
   "target": {
    "id": "https://data.goldenagents.org/datasets/dh2020/canvas/A16098000171",
    "selector": {
     "type": "SvgSelector",
     "value": "<svg xmlns=\"http://www.w3.org/2000/svg\"><path fill-rule=\"evenodd\" fill=\"#66cc99\" stroke=\"#555555\" stroke-width=\"1\" fill-opacity=\"0.08\" d=\"M 870,2610 L 935,2610 L 1000,2612 L 1065,2612 L 1130,2612 L 1195,2612 L 1260,2612 L 1325,2612 L 1390,2612 L 1455,2612 L 1520,2612 L 1585,2612 L 1650,2612 L 1715,2612 L 1780,2614 L 1845,2615 L 1910,2616 L 1975,2618 L 2040,2622 L 2105,2626 L 2170,2630 L 2170,2593 L 2105,2589 L 2040,2585 L 1975,2581 L 1910,2579 L 1845,2578 L 1780,2577 L 1715,2575 L 1650,2575 L 1585,2575 L 1520,2575 L 1455,2575 L 1390,2575 L 1325,2575 L 1260,2575 L 1195,2575 L 1130,2575 L 1065,2575 L 1000,2575 L 935,2573 L 870,2573 L 870,2610 Z\"/></svg>"
    }
   }
  },
  {
   "@context": "http://iiif.io/api/presentation/3/context.json",
   "id": "https://data.goldenagents.org/datasets/dh2020/annotation/A16098000171/r2l33",
   "type": "Annotation",
   "motivation": "supplementing",
   "body": [
    {
     "type": "TextualBody",
     "language": "nl",
     "value": "moer"
    }
   ],
   "target": {
    "id": "https://data.goldenagents.org/datasets/dh2020/canvas/A16098000171",
    "selector": {
     "type": "SvgSelector",
     "value": "<svg xmlns=\"http://www.w3.org/2000/svg\"><path fill-rule=\"evenodd\" fill=\"#66cc99\" stroke=\"#555555\" stroke-width=\"1\" fill-opacity=\"0.08\" d=\"M 1152,2662 L 1180,2664 L 1208,2664 L 1236,2664 L 1265,2664 L 1293,2664 L 1321,2665 L 1350,2668 L 1350,2631 L 1321,2628 L 1293,2627 L 1265,2627 L 1236,2627 L 1208,2627 L 1180,2627 L 1152,2625 L 1152,2662 Z\"/></svg>"
    }
   }
  },
  {
   "@context": "http://iiif.io/api/presentation/3/context.json",
   "id": "https://data.goldenagents.org/datasets/dh2020/annotation/A16098000171/r2l35",
   "type": "Annotation",
   "motivation": "supplementing",
   "body": [
    {
     "type": "TextualBody",
     "language": "nl",
     "value": "Een lavender dwaal"
    }
   ],
   "target": {
    "id": "https://data.goldenagents.org/datasets/dh2020/canvas/A16098000171",
    "selector": {
     "type": "SvgSelector",
     "value": "<svg xmlns=\"http://www.w3.org/2000/svg\"><path fill-rule=\"evenodd\" fill=\"#66cc99\" stroke=\"#555555\" stroke-width=\"1\" fill-opacity=\"0.08\" d=\"M 868,2705 L 909,2710 L 950,2715 L 991,2718 L 1032,2722 L 1073,2725 L 1114,2727 L 1155,2727 L 1196,2729 L 1237,2729 L 1278,2729 L 1319,2729 L 1360,2729 L 1401,2729 L 1442,2729 L 1483,2727 L 1524,2727 L 1565,2727 L 1606,2727 L 1647,2727 L 1688,2727 L 1688,2682 L 1647,2682 L 1606,2682 L 1565,2682 L 1524,2682 L 1483,2682 L 1442,2684 L 1401,2684 L 1360,2684 L 1319,2684 L 1278,2684 L 1237,2684 L 1196,2684 L 1155,2682 L 1114,2682 L 1073,2680 L 1032,2677 L 991,2673 L 950,2670 L 909,2665 L 868,2660 L 868,2705 Z\"/></svg>"
    }
   }
  },
  {
   "@context": "http://iiif.io/api/presentation/3/context.json",
   "id": "https://data.goldenagents.org/datasets/dh2020/annotation/A16098000171/r2l36",
   "type": "Annotation",
   "motivation": "supplementing",
   "body": [
    {
     "type": "TextualBody",
     "language": "nl",
     "value": "Een pavij tafellaken van seven elle"
    }
   ],
   "target": {
    "id": "https://data.goldenagents.org/datasets/dh2020/canvas/A16098000171",
    "selector": {
     "type": "SvgSelector",
     "value": "<svg xmlns=\"http://www.w3.org/2000/svg\"><path fill-rule=\"evenodd\" fill=\"#66cc99\" stroke=\"#555555\" stroke-width=\"1\" fill-opacity=\"0.08\" d=\"M 870,2788 L 933,2792 L 996,2794 L 1060,2797 L 1123,2800 L 1187,2800 L 1250,2802 L 1313,2802 L 1377,2802 L 1440,2802 L 1504,2804 L 1567,2804 L 1630,2804 L 1694,2804 L 1757,2804 L 1821,2804 L 1884,2806 L 1947,2807 L 2011,2810 L 2074,2813 L 2138,2816 L 2138,2768 L 2074,2765 L 2011,2762 L 1947,2759 L 1884,2758 L 1821,2756 L 1757,2756 L 1694,2756 L 1630,2756 L 1567,2756 L 1504,2756 L 1440,2754 L 1377,2754 L 1313,2754 L 1250,2754 L 1187,2752 L 1123,2752 L 1060,2749 L 996,2746 L 933,2744 L 870,2740 L 870,2788 Z\"/></svg>"
    }
   }
  },
  {
   "@context": "http://iiif.io/api/presentation/3/context.json",
   "id": "https://data.goldenagents.org/datasets/dh2020/annotation/A16098000171/r2l37",
   "type": "Annotation",
   "motivation": "supplementing",
   "body": [
    {
     "type": "TextualBody",
     "language": "nl",
     "value": "Nogh een pavij tafellaken van"
    }
   ],
   "target": {
    "id": "https://data.goldenagents.org/datasets/dh2020/canvas/A16098000171",
    "selector": {
     "type": "SvgSelector",
     "value": "<svg xmlns=\"http://www.w3.org/2000/svg\"><path fill-rule=\"evenodd\" fill=\"#66cc99\" stroke=\"#555555\" stroke-width=\"1\" fill-opacity=\"0.08\" d=\"M 868,2862 L 927,2866 L 986,2869 L 1046,2872 L 1105,2874 L 1165,2876 L 1224,2878 L 1283,2878 L 1343,2880 L 1402,2880 L 1462,2882 L 1521,2882 L 1580,2882 L 1640,2882 L 1699,2884 L 1759,2884 L 1818,2884 L 1877,2886 L 1937,2886 L 1996,2886 L 2056,2888 L 2056,2846 L 1996,2844 L 1937,2844 L 1877,2844 L 1818,2842 L 1759,2842 L 1699,2842 L 1640,2840 L 1580,2840 L 1521,2840 L 1462,2840 L 1402,2838 L 1343,2838 L 1283,2836 L 1224,2836 L 1165,2834 L 1105,2832 L 1046,2830 L 986,2827 L 927,2824 L 868,2820 L 868,2862 Z\"/></svg>"
    }
   }
  },
  {
   "@context": "http://iiif.io/api/presentation/3/context.json",
   "id": "https://data.goldenagents.org/datasets/dh2020/annotation/A16098000171/r2l38",
   "type": "Annotation",
   "motivation": "supplementing",
   "body": [
    {
     "type": "TextualBody",
     "language": "nl",
     "value": "vier elle"
    }
   ],
   "target": {
    "id": "https://data.goldenagents.org/datasets/dh2020/canvas/A16098000171",
    "selector": {
     "type": "SvgSelector",
     "value": "<svg xmlns=\"http://www.w3.org/2000/svg\"><path fill-rule=\"evenodd\" fill=\"#66cc99\" stroke=\"#555555\" stroke-width=\"1\" fill-opacity=\"0.08\" d=\"M 1104,2932 L 1130,2933 L 1156,2934 L 1182,2934 L 1208,2934 L 1234,2934 L 1260,2934 L 1287,2936 L 1313,2936 L 1339,2937 L 1365,2938 L 1391,2940 L 1417,2942 L 1444,2944 L 1444,2902 L 1417,2900 L 1391,2898 L 1365,2896 L 1339,2895 L 1313,2894 L 1287,2894 L 1260,2892 L 1234,2892 L 1208,2892 L 1182,2892 L 1156,2892 L 1130,2891 L 1104,2890 L 1104,2932 Z\"/></svg>"
    }
   }
  },
  {
   "@context": "http://iiif.io/api/presentation/3/context.json",
   "id": "https://data.goldenagents.org/datasets/dh2020/annotation/A16098000171/r2l39",
   "type": "Annotation",
   "motivation": "supplementing",
   "body": [
    {
     "type": "TextualBody",
     "language": "nl",
     "value": "Nogh een pavij tafellaken van een"
    }
   ],
   "target": {
    "id": "https://data.goldenagents.org/datasets/dh2020/canvas/A16098000171",
    "selector": {
     "type": "SvgSelector",
     "value": "<svg xmlns=\"http://www.w3.org/2000/svg\"><path fill-rule=\"evenodd\" fill=\"#66cc99\" stroke=\"#555555\" stroke-width=\"1\" fill-opacity=\"0.08\" d=\"M 824,3006 L 884,3012 L 944,3014 L 1004,3016 L 1064,3016 L 1125,3018 L 1185,3016 L 1245,3016 L 1305,3015 L 1365,3014 L 1426,3013 L 1486,3012 L 1546,3010 L 1606,3010 L 1666,3010 L 1727,3010 L 1787,3011 L 1847,3013 L 1907,3017 L 1967,3020 L 2028,3026 L 2028,2978 L 1967,2972 L 1907,2969 L 1847,2965 L 1787,2963 L 1727,2962 L 1666,2962 L 1606,2962 L 1546,2962 L 1486,2964 L 1426,2965 L 1365,2966 L 1305,2967 L 1245,2968 L 1185,2968 L 1125,2970 L 1064,2968 L 1004,2968 L 944,2966 L 884,2964 L 824,2958 L 824,3006 Z\"/></svg>"
    }
   }
  },
  {
   "@context": "http://iiif.io/api/presentation/3/context.json",
   "id": "https://data.goldenagents.org/datasets/dh2020/annotation/A16098000171/r2l40",
   "type": "Annotation",
   "motivation": "supplementing",
   "body": [
    {
     "type": "TextualBody",
     "language": "nl",
     "value": "ende een half ell"
    }
   ],
   "target": {
    "id": "https://data.goldenagents.org/datasets/dh2020/canvas/A16098000171",
    "selector": {
     "type": "SvgSelector",
     "value": "<svg xmlns=\"http://www.w3.org/2000/svg\"><path fill-rule=\"evenodd\" fill=\"#66cc99\" stroke=\"#555555\" stroke-width=\"1\" fill-opacity=\"0.08\" d=\"M 1086,3084 L 1118,3084 L 1150,3086 L 1182,3086 L 1214,3088 L 1247,3088 L 1279,3088 L 1311,3088 L 1343,3088 L 1375,3088 L 1408,3087 L 1440,3086 L 1472,3086 L 1504,3086 L 1536,3084 L 1569,3084 L 1601,3084 L 1633,3082 L 1665,3082 L 1697,3082 L 1730,3080 L 1730,3032 L 1697,3034 L 1665,3034 L 1633,3034 L 1601,3036 L 1569,3036 L 1536,3036 L 1504,3038 L 1472,3038 L 1440,3038 L 1408,3039 L 1375,3040 L 1343,3040 L 1311,3040 L 1279,3040 L 1247,3040 L 1214,3040 L 1182,3038 L 1150,3038 L 1118,3036 L 1086,3036 L 1086,3084 Z\"/></svg>"
    }
   }
  },
  {
   "@context": "http://iiif.io/api/presentation/3/context.json",
   "id": "https://data.goldenagents.org/datasets/dh2020/annotation/A16098000171/r2l41",
   "type": "Annotation",
   "motivation": "supplementing",
   "body": [
    {
     "type": "TextualBody",
     "language": "nl",
     "value": "Nogh een pavij tafellaken van 2\u00bd el"
    }
   ],
   "target": {
    "id": "https://data.goldenagents.org/datasets/dh2020/canvas/A16098000171",
    "selector": {
     "type": "SvgSelector",
     "value": "<svg xmlns=\"http://www.w3.org/2000/svg\"><path fill-rule=\"evenodd\" fill=\"#66cc99\" stroke=\"#555555\" stroke-width=\"1\" fill-opacity=\"0.08\" d=\"M 840,3144 L 907,3150 L 974,3157 L 1041,3160 L 1108,3164 L 1175,3166 L 1242,3166 L 1309,3168 L 1376,3168 L 1443,3166 L 1511,3166 L 1578,3164 L 1645,3164 L 1712,3162 L 1779,3162 L 1846,3162 L 1913,3162 L 1980,3164 L 2047,3166 L 2114,3168 L 2182,3174 L 2182,3126 L 2114,3120 L 2047,3118 L 1980,3116 L 1913,3114 L 1846,3114 L 1779,3114 L 1712,3114 L 1645,3116 L 1578,3116 L 1511,3118 L 1443,3118 L 1376,3120 L 1309,3120 L 1242,3118 L 1175,3118 L 1108,3116 L 1041,3112 L 974,3109 L 907,3102 L 840,3096 L 840,3144 Z\"/></svg>"
    }
   }
  },
  {
   "@context": "http://iiif.io/api/presentation/3/context.json",
   "id": "https://data.goldenagents.org/datasets/dh2020/annotation/A16098000171/r2l42",
   "type": "Annotation",
   "motivation": "supplementing",
   "body": [
    {
     "type": "TextualBody",
     "language": "nl",
     "value": "Een kruijsbeelt tafellaken van"
    }
   ],
   "target": {
    "id": "https://data.goldenagents.org/datasets/dh2020/canvas/A16098000171",
    "selector": {
     "type": "SvgSelector",
     "value": "<svg xmlns=\"http://www.w3.org/2000/svg\"><path fill-rule=\"evenodd\" fill=\"#66cc99\" stroke=\"#555555\" stroke-width=\"1\" fill-opacity=\"0.08\" d=\"M 870,3232 L 930,3237 L 990,3241 L 1051,3243 L 1111,3246 L 1172,3248 L 1232,3248 L 1292,3250 L 1353,3250 L 1413,3250 L 1474,3250 L 1534,3250 L 1594,3250 L 1655,3250 L 1715,3250 L 1776,3250 L 1836,3250 L 1896,3250 L 1957,3250 L 2017,3250 L 2078,3252 L 2078,3204 L 2017,3202 L 1957,3202 L 1896,3202 L 1836,3202 L 1776,3202 L 1715,3202 L 1655,3202 L 1594,3202 L 1534,3202 L 1474,3202 L 1413,3202 L 1353,3202 L 1292,3202 L 1232,3200 L 1172,3200 L 1111,3198 L 1051,3195 L 990,3193 L 930,3189 L 870,3184 L 870,3232 Z\"/></svg>"
    }
   }
  },
  {
   "@context": "http://iiif.io/api/presentation/3/context.json",
   "id": "https://data.goldenagents.org/datasets/dh2020/annotation/A16098000171/r2l43",
   "type": "Annotation",
   "motivation": "supplementing",
   "body": [
    {
     "type": "TextualBody",
     "language": "nl",
     "value": "Een tafellaken van lavender van"
    }
   ],
   "target": {
    "id": "https://data.goldenagents.org/datasets/dh2020/canvas/A16098000171",
    "selector": {
     "type": "SvgSelector",
     "value": "<svg xmlns=\"http://www.w3.org/2000/svg\"><path fill-rule=\"evenodd\" fill=\"#66cc99\" stroke=\"#555555\" stroke-width=\"1\" fill-opacity=\"0.08\" d=\"M 880,3347 L 938,3354 L 996,3357 L 1054,3361 L 1112,3363 L 1170,3365 L 1228,3365 L 1286,3364 L 1344,3363 L 1402,3361 L 1461,3360 L 1519,3359 L 1577,3357 L 1635,3355 L 1693,3355 L 1751,3353 L 1809,3354 L 1867,3355 L 1925,3357 L 1983,3359 L 2042,3365 L 2042,3331 L 1983,3325 L 1925,3323 L 1867,3321 L 1809,3320 L 1751,3319 L 1693,3321 L 1635,3321 L 1577,3323 L 1519,3325 L 1461,3326 L 1402,3327 L 1344,3329 L 1286,3330 L 1228,3331 L 1170,3331 L 1112,3329 L 1054,3327 L 996,3323 L 938,3320 L 880,3313 L 880,3347 Z\"/></svg>"
    }
   }
  },
  {
   "@context": "http://iiif.io/api/presentation/3/context.json",
   "id": "https://data.goldenagents.org/datasets/dh2020/annotation/A16098000171/r2l44",
   "type": "Annotation",
   "motivation": "supplementing",
   "body": [
    {
     "type": "TextualBody",
     "language": "nl",
     "value": "vijff ellen"
    }
   ],
   "target": {
    "id": "https://data.goldenagents.org/datasets/dh2020/canvas/A16098000171",
    "selector": {
     "type": "SvgSelector",
     "value": "<svg xmlns=\"http://www.w3.org/2000/svg\"><path fill-rule=\"evenodd\" fill=\"#66cc99\" stroke=\"#555555\" stroke-width=\"1\" fill-opacity=\"0.08\" d=\"M 1156,3413 L 1181,3412 L 1207,3411 L 1233,3411 L 1259,3411 L 1284,3411 L 1310,3411 L 1336,3412 L 1362,3413 L 1387,3414 L 1413,3415 L 1439,3415 L 1465,3416 L 1490,3417 L 1516,3417 L 1542,3417 L 1568,3417 L 1568,3384 L 1542,3384 L 1516,3384 L 1490,3384 L 1465,3383 L 1439,3382 L 1413,3382 L 1387,3381 L 1362,3380 L 1336,3379 L 1310,3378 L 1284,3378 L 1259,3378 L 1233,3378 L 1207,3378 L 1181,3379 L 1156,3380 L 1156,3413 Z\"/></svg>"
    }
   }
  },
  {
   "@context": "http://iiif.io/api/presentation/3/context.json",
   "id": "https://data.goldenagents.org/datasets/dh2020/annotation/A16098000171/r2l45",
   "type": "Annotation",
   "motivation": "supplementing",
   "body": [
    {
     "type": "TextualBody",
     "language": "nl",
     "value": "Nogh een tafellaken lavender van"
    }
   ],
   "target": {
    "id": "https://data.goldenagents.org/datasets/dh2020/canvas/A16098000171",
    "selector": {
     "type": "SvgSelector",
     "value": "<svg xmlns=\"http://www.w3.org/2000/svg\"><path fill-rule=\"evenodd\" fill=\"#66cc99\" stroke=\"#555555\" stroke-width=\"1\" fill-opacity=\"0.08\" d=\"M 846,3465 L 908,3469 L 970,3473 L 1032,3475 L 1094,3477 L 1156,3478 L 1218,3479 L 1280,3479 L 1342,3479 L 1404,3477 L 1466,3477 L 1528,3477 L 1590,3477 L 1652,3475 L 1714,3475 L 1776,3476 L 1838,3477 L 1900,3479 L 1962,3481 L 2024,3483 L 2086,3487 L 2086,3454 L 2024,3450 L 1962,3448 L 1900,3446 L 1838,3444 L 1776,3443 L 1714,3442 L 1652,3442 L 1590,3444 L 1528,3444 L 1466,3444 L 1404,3444 L 1342,3446 L 1280,3446 L 1218,3446 L 1156,3445 L 1094,3444 L 1032,3442 L 970,3440 L 908,3436 L 846,3432 L 846,3465 Z\"/></svg>"
    }
   }
  },
  {
   "@context": "http://iiif.io/api/presentation/3/context.json",
   "id": "https://data.goldenagents.org/datasets/dh2020/annotation/A16098000171/r2l46",
   "type": "Annotation",
   "motivation": "supplementing",
   "body": [
    {
     "type": "TextualBody",
     "language": "nl",
     "value": "vier ellen"
    }
   ],
   "target": {
    "id": "https://data.goldenagents.org/datasets/dh2020/canvas/A16098000171",
    "selector": {
     "type": "SvgSelector",
     "value": "<svg xmlns=\"http://www.w3.org/2000/svg\"><path fill-rule=\"evenodd\" fill=\"#66cc99\" stroke=\"#555555\" stroke-width=\"1\" fill-opacity=\"0.08\" d=\"M 1276,3523 L 1301,3528 L 1327,3530 L 1352,3531 L 1378,3531 L 1403,3531 L 1429,3531 L 1455,3530 L 1480,3529 L 1506,3529 L 1531,3529 L 1557,3529 L 1582,3530 L 1608,3532 L 1634,3535 L 1634,3502 L 1608,3499 L 1582,3497 L 1557,3496 L 1531,3496 L 1506,3496 L 1480,3496 L 1455,3497 L 1429,3498 L 1403,3498 L 1378,3498 L 1352,3498 L 1327,3497 L 1301,3495 L 1276,3490 L 1276,3523 Z\"/></svg>"
    }
   }
  },
  {
   "@context": "http://iiif.io/api/presentation/3/context.json",
   "id": "https://data.goldenagents.org/datasets/dh2020/annotation/A16098000171/r2l47",
   "type": "Annotation",
   "motivation": "supplementing",
   "body": [
    {
     "type": "TextualBody",
     "language": "nl",
     "value": "Nogh een tafellaken lavender van"
    }
   ],
   "target": {
    "id": "https://data.goldenagents.org/datasets/dh2020/canvas/A16098000171",
    "selector": {
     "type": "SvgSelector",
     "value": "<svg xmlns=\"http://www.w3.org/2000/svg\"><path fill-rule=\"evenodd\" fill=\"#66cc99\" stroke=\"#555555\" stroke-width=\"1\" fill-opacity=\"0.08\" d=\"M 866,3583 L 921,3585 L 977,3585 L 1033,3585 L 1088,3586 L 1144,3587 L 1200,3587 L 1255,3588 L 1311,3589 L 1367,3589 L 1423,3591 L 1478,3591 L 1534,3591 L 1590,3591 L 1645,3593 L 1701,3593 L 1757,3593 L 1812,3595 L 1868,3595 L 1924,3595 L 1980,3595 L 1980,3556 L 1924,3556 L 1868,3556 L 1812,3556 L 1757,3554 L 1701,3554 L 1645,3554 L 1590,3552 L 1534,3552 L 1478,3552 L 1423,3552 L 1367,3550 L 1311,3550 L 1255,3549 L 1200,3548 L 1144,3548 L 1088,3547 L 1033,3546 L 977,3546 L 921,3546 L 866,3544 L 866,3583 Z\"/></svg>"
    }
   }
  },
  {
   "@context": "http://iiif.io/api/presentation/3/context.json",
   "id": "https://data.goldenagents.org/datasets/dh2020/annotation/A16098000171/r2l48",
   "type": "Annotation",
   "motivation": "supplementing",
   "body": [
    {
     "type": "TextualBody",
     "language": "nl",
     "value": "twee ellen"
    }
   ],
   "target": {
    "id": "https://data.goldenagents.org/datasets/dh2020/canvas/A16098000171",
    "selector": {
     "type": "SvgSelector",
     "value": "<svg xmlns=\"http://www.w3.org/2000/svg\"><path fill-rule=\"evenodd\" fill=\"#66cc99\" stroke=\"#555555\" stroke-width=\"1\" fill-opacity=\"0.08\" d=\"M 1096,3637 L 1121,3638 L 1147,3639 L 1173,3639 L 1199,3639 L 1224,3639 L 1250,3639 L 1276,3640 L 1302,3641 L 1328,3641 L 1353,3641 L 1379,3641 L 1405,3643 L 1431,3645 L 1457,3645 L 1482,3647 L 1508,3647 L 1534,3650 L 1560,3652 L 1586,3655 L 1586,3622 L 1560,3619 L 1534,3617 L 1508,3614 L 1482,3614 L 1457,3612 L 1431,3612 L 1405,3610 L 1379,3608 L 1353,3608 L 1328,3608 L 1302,3608 L 1276,3607 L 1250,3606 L 1224,3606 L 1199,3606 L 1173,3606 L 1147,3606 L 1121,3605 L 1096,3604 L 1096,3637 Z\"/></svg>"
    }
   }
  },
  {
   "@context": "http://iiif.io/api/presentation/3/context.json",
   "id": "https://data.goldenagents.org/datasets/dh2020/annotation/A16098000171/r2l49",
   "type": "Annotation",
   "motivation": "supplementing",
   "body": [
    {
     "type": "TextualBody",
     "language": "nl",
     "value": "Een tafellaken uijters beelt van"
    }
   ],
   "target": {
    "id": "https://data.goldenagents.org/datasets/dh2020/canvas/A16098000171",
    "selector": {
     "type": "SvgSelector",
     "value": "<svg xmlns=\"http://www.w3.org/2000/svg\"><path fill-rule=\"evenodd\" fill=\"#66cc99\" stroke=\"#555555\" stroke-width=\"1\" fill-opacity=\"0.08\" d=\"M 850,3694 L 910,3698 L 971,3700 L 1032,3702 L 1093,3704 L 1154,3704 L 1214,3704 L 1275,3704 L 1336,3704 L 1397,3702 L 1458,3701 L 1518,3700 L 1579,3698 L 1640,3696 L 1701,3695 L 1762,3692 L 1822,3690 L 1883,3688 L 1944,3688 L 2005,3686 L 2066,3684 L 2066,3653 L 2005,3655 L 1944,3657 L 1883,3657 L 1822,3659 L 1762,3661 L 1701,3664 L 1640,3665 L 1579,3667 L 1518,3669 L 1458,3670 L 1397,3671 L 1336,3673 L 1275,3673 L 1214,3673 L 1154,3673 L 1093,3673 L 1032,3671 L 971,3669 L 910,3667 L 850,3663 L 850,3694 Z\"/></svg>"
    }
   }
  },
  {
   "@context": "http://iiif.io/api/presentation/3/context.json",
   "id": "https://data.goldenagents.org/datasets/dh2020/annotation/A16098000171/r2l50",
   "type": "Annotation",
   "motivation": "supplementing",
   "body": [
    {
     "type": "TextualBody",
     "language": "nl",
     "value": "twee ellen,"
    }
   ],
   "target": {
    "id": "https://data.goldenagents.org/datasets/dh2020/canvas/A16098000171",
    "selector": {
     "type": "SvgSelector",
     "value": "<svg xmlns=\"http://www.w3.org/2000/svg\"><path fill-rule=\"evenodd\" fill=\"#66cc99\" stroke=\"#555555\" stroke-width=\"1\" fill-opacity=\"0.08\" d=\"M 1028,3759 L 1053,3761 L 1078,3762 L 1103,3763 L 1128,3763 L 1154,3763 L 1179,3763 L 1204,3763 L 1229,3763 L 1255,3763 L 1280,3763 L 1305,3765 L 1330,3765 L 1355,3766 L 1381,3768 L 1406,3769 L 1431,3772 L 1456,3774 L 1482,3779 L 1482,3739 L 1456,3734 L 1431,3732 L 1406,3729 L 1381,3728 L 1355,3726 L 1330,3725 L 1305,3725 L 1280,3723 L 1255,3723 L 1229,3723 L 1204,3723 L 1179,3723 L 1154,3723 L 1128,3723 L 1103,3723 L 1078,3722 L 1053,3721 L 1028,3719 L 1028,3759 Z\"/></svg>"
    }
   }
  },
  {
   "@context": "http://iiif.io/api/presentation/3/context.json",
   "id": "https://data.goldenagents.org/datasets/dh2020/annotation/A16098000171/r3l1",
   "type": "Annotation",
   "motivation": "supplementing",
   "body": [
    {
     "type": "TextualBody",
     "language": "nl",
     "value": "30"
    }
   ],
   "target": {
    "id": "https://data.goldenagents.org/datasets/dh2020/canvas/A16098000171",
    "selector": {
     "type": "SvgSelector",
     "value": "<svg xmlns=\"http://www.w3.org/2000/svg\"><path fill-rule=\"evenodd\" fill=\"#66cc99\" stroke=\"#555555\" stroke-width=\"1\" fill-opacity=\"0.08\" d=\"M 4752,206 L 4778,212 L 4805,211 L 4832,214 L 4832,153 L 4805,150 L 4778,151 L 4752,145 L 4752,206 Z\"/></svg>"
    }
   }
  },
  {
   "@context": "http://iiif.io/api/presentation/3/context.json",
   "id": "https://data.goldenagents.org/datasets/dh2020/annotation/A16098000171/r3l2",
   "type": "Annotation",
   "motivation": "supplementing",
   "body": [
    {
     "type": "TextualBody",
     "language": "nl",
     "value": "37"
    }
   ],
   "target": {
    "id": "https://data.goldenagents.org/datasets/dh2020/canvas/A16098000171",
    "selector": {
     "type": "SvgSelector",
     "value": "<svg xmlns=\"http://www.w3.org/2000/svg\"><path fill-rule=\"evenodd\" fill=\"#66cc99\" stroke=\"#555555\" stroke-width=\"1\" fill-opacity=\"0.08\" d=\"M 4766,296 L 4791,298 L 4816,300 L 4841,301 L 4866,304 L 4866,243 L 4841,240 L 4816,239 L 4791,237 L 4766,235 L 4766,296 Z\"/></svg>"
    }
   }
  },
  {
   "@context": "http://iiif.io/api/presentation/3/context.json",
   "id": "https://data.goldenagents.org/datasets/dh2020/annotation/A16098000171/r3l3",
   "type": "Annotation",
   "motivation": "supplementing",
   "body": [
    {
     "type": "TextualBody",
     "language": "nl",
     "value": "Een tafellaken van lavender met"
    }
   ],
   "target": {
    "id": "https://data.goldenagents.org/datasets/dh2020/canvas/A16098000171",
    "selector": {
     "type": "SvgSelector",
     "value": "<svg xmlns=\"http://www.w3.org/2000/svg\"><path fill-rule=\"evenodd\" fill=\"#66cc99\" stroke=\"#555555\" stroke-width=\"1\" fill-opacity=\"0.08\" d=\"M 3164,303 L 3231,303 L 3298,304 L 3365,305 L 3432,305 L 3500,305 L 3567,305 L 3634,305 L 3701,305 L 3768,305 L 3836,305 L 3903,305 L 3970,305 L 4037,305 L 4104,305 L 4172,305 L 4239,305 L 4306,305 L 4373,305 L 4440,307 L 4508,307 L 4508,250 L 4440,250 L 4373,248 L 4306,248 L 4239,248 L 4172,248 L 4104,248 L 4037,248 L 3970,248 L 3903,248 L 3836,248 L 3768,248 L 3701,248 L 3634,248 L 3567,248 L 3500,248 L 3432,248 L 3365,248 L 3298,247 L 3231,246 L 3164,246 L 3164,303 Z\"/></svg>"
    }
   }
  },
  {
   "@context": "http://iiif.io/api/presentation/3/context.json",
   "id": "https://data.goldenagents.org/datasets/dh2020/annotation/A16098000171/r3l4",
   "type": "Annotation",
   "motivation": "supplementing",
   "body": [
    {
     "type": "TextualBody",
     "language": "nl",
     "value": "roosen van drij ellen"
    }
   ],
   "target": {
    "id": "https://data.goldenagents.org/datasets/dh2020/canvas/A16098000171",
    "selector": {
     "type": "SvgSelector",
     "value": "<svg xmlns=\"http://www.w3.org/2000/svg\"><path fill-rule=\"evenodd\" fill=\"#66cc99\" stroke=\"#555555\" stroke-width=\"1\" fill-opacity=\"0.08\" d=\"M 3442,388 L 3474,388 L 3506,387 L 3538,386 L 3570,385 L 3602,384 L 3634,383 L 3666,382 L 3698,382 L 3730,382 L 3762,380 L 3794,380 L 3826,380 L 3858,380 L 3890,380 L 3922,378 L 3954,378 L 3986,378 L 4018,378 L 4050,378 L 4082,378 L 4082,323 L 4050,323 L 4018,323 L 3986,323 L 3954,323 L 3922,323 L 3890,325 L 3858,325 L 3826,325 L 3794,325 L 3762,325 L 3730,327 L 3698,327 L 3666,327 L 3634,328 L 3602,329 L 3570,330 L 3538,331 L 3506,332 L 3474,333 L 3442,333 L 3442,388 Z\"/></svg>"
    }
   }
  },
  {
   "@context": "http://iiif.io/api/presentation/3/context.json",
   "id": "https://data.goldenagents.org/datasets/dh2020/annotation/A16098000171/r3l5",
   "type": "Annotation",
   "motivation": "supplementing",
   "body": [
    {
     "type": "TextualBody",
     "language": "nl",
     "value": "Opte Solder,"
    }
   ],
   "target": {
    "id": "https://data.goldenagents.org/datasets/dh2020/canvas/A16098000171",
    "selector": {
     "type": "SvgSelector",
     "value": "<svg xmlns=\"http://www.w3.org/2000/svg\"><path fill-rule=\"evenodd\" fill=\"#66cc99\" stroke=\"#555555\" stroke-width=\"1\" fill-opacity=\"0.08\" d=\"M 3470,526 L 3497,525 L 3524,523 L 3551,522 L 3578,520 L 3605,520 L 3632,518 L 3659,516 L 3686,514 L 3713,512 L 3740,510 L 3767,509 L 3794,507 L 3821,506 L 3848,506 L 3875,506 L 3902,506 L 3929,506 L 3956,508 L 3983,509 L 4010,512 L 4010,451 L 3983,448 L 3956,447 L 3929,445 L 3902,445 L 3875,445 L 3848,445 L 3821,445 L 3794,446 L 3767,448 L 3740,449 L 3713,451 L 3686,453 L 3659,455 L 3632,457 L 3605,459 L 3578,459 L 3551,461 L 3524,462 L 3497,464 L 3470,465 L 3470,526 Z\"/></svg>"
    }
   }
  },
  {
   "@context": "http://iiif.io/api/presentation/3/context.json",
   "id": "https://data.goldenagents.org/datasets/dh2020/annotation/A16098000171/r3l6",
   "type": "Annotation",
   "motivation": "supplementing",
   "body": [
    {
     "type": "TextualBody",
     "language": "nl",
     "value": "Acht kleerstokken"
    }
   ],
   "target": {
    "id": "https://data.goldenagents.org/datasets/dh2020/canvas/A16098000171",
    "selector": {
     "type": "SvgSelector",
     "value": "<svg xmlns=\"http://www.w3.org/2000/svg\"><path fill-rule=\"evenodd\" fill=\"#66cc99\" stroke=\"#555555\" stroke-width=\"1\" fill-opacity=\"0.08\" d=\"M 3172,655 L 3209,651 L 3247,648 L 3285,645 L 3323,641 L 3361,639 L 3399,636 L 3437,635 L 3475,632 L 3513,631 L 3551,629 L 3588,629 L 3626,627 L 3664,627 L 3702,625 L 3740,625 L 3778,625 L 3816,624 L 3854,623 L 3892,623 L 3930,621 L 3930,575 L 3892,577 L 3854,577 L 3816,578 L 3778,579 L 3740,579 L 3702,579 L 3664,581 L 3626,581 L 3588,583 L 3551,583 L 3513,585 L 3475,586 L 3437,589 L 3399,590 L 3361,593 L 3323,595 L 3285,599 L 3247,602 L 3209,605 L 3172,609 L 3172,655 Z\"/></svg>"
    }
   }
  },
  {
   "@context": "http://iiif.io/api/presentation/3/context.json",
   "id": "https://data.goldenagents.org/datasets/dh2020/annotation/A16098000171/r3l7",
   "type": "Annotation",
   "motivation": "supplementing",
   "body": [
    {
     "type": "TextualBody",
     "language": "nl",
     "value": "Een vleesgaffel"
    }
   ],
   "target": {
    "id": "https://data.goldenagents.org/datasets/dh2020/canvas/A16098000171",
    "selector": {
     "type": "SvgSelector",
     "value": "<svg xmlns=\"http://www.w3.org/2000/svg\"><path fill-rule=\"evenodd\" fill=\"#66cc99\" stroke=\"#555555\" stroke-width=\"1\" fill-opacity=\"0.08\" d=\"M 3216,713 L 3253,715 L 3290,717 L 3327,717 L 3364,717 L 3402,717 L 3439,717 L 3476,715 L 3513,715 L 3550,713 L 3588,713 L 3625,711 L 3662,711 L 3699,709 L 3736,709 L 3774,709 L 3811,709 L 3848,709 L 3885,710 L 3922,711 L 3960,713 L 3960,667 L 3922,665 L 3885,664 L 3848,663 L 3811,663 L 3774,663 L 3736,663 L 3699,663 L 3662,665 L 3625,665 L 3588,667 L 3550,667 L 3513,669 L 3476,669 L 3439,671 L 3402,671 L 3364,671 L 3327,671 L 3290,671 L 3253,669 L 3216,667 L 3216,713 Z\"/></svg>"
    }
   }
  },
  {
   "@context": "http://iiif.io/api/presentation/3/context.json",
   "id": "https://data.goldenagents.org/datasets/dh2020/annotation/A16098000171/r3l8",
   "type": "Annotation",
   "motivation": "supplementing",
   "body": [
    {
     "type": "TextualBody",
     "language": "nl",
     "value": "Een vurenhoute taaffel"
    }
   ],
   "target": {
    "id": "https://data.goldenagents.org/datasets/dh2020/canvas/A16098000171",
    "selector": {
     "type": "SvgSelector",
     "value": "<svg xmlns=\"http://www.w3.org/2000/svg\"><path fill-rule=\"evenodd\" fill=\"#66cc99\" stroke=\"#555555\" stroke-width=\"1\" fill-opacity=\"0.08\" d=\"M 3188,796 L 3240,794 L 3293,794 L 3346,792 L 3399,790 L 3452,789 L 3505,788 L 3558,786 L 3611,785 L 3664,784 L 3717,782 L 3769,780 L 3822,780 L 3875,780 L 3928,778 L 3981,778 L 4034,778 L 4087,779 L 4140,780 L 4193,781 L 4246,782 L 4246,733 L 4193,732 L 4140,731 L 4087,730 L 4034,729 L 3981,729 L 3928,729 L 3875,731 L 3822,731 L 3769,731 L 3717,733 L 3664,735 L 3611,736 L 3558,737 L 3505,739 L 3452,740 L 3399,741 L 3346,743 L 3293,745 L 3240,745 L 3188,747 L 3188,796 Z\"/></svg>"
    }
   }
  },
  {
   "@context": "http://iiif.io/api/presentation/3/context.json",
   "id": "https://data.goldenagents.org/datasets/dh2020/annotation/A16098000171/r3l9",
   "type": "Annotation",
   "motivation": "supplementing",
   "body": [
    {
     "type": "TextualBody",
     "language": "nl",
     "value": "Twee tobbetjes,"
    }
   ],
   "target": {
    "id": "https://data.goldenagents.org/datasets/dh2020/canvas/A16098000171",
    "selector": {
     "type": "SvgSelector",
     "value": "<svg xmlns=\"http://www.w3.org/2000/svg\"><path fill-rule=\"evenodd\" fill=\"#66cc99\" stroke=\"#555555\" stroke-width=\"1\" fill-opacity=\"0.08\" d=\"M 3194,873 L 3229,873 L 3264,873 L 3300,871 L 3335,871 L 3371,869 L 3406,869 L 3441,869 L 3477,869 L 3512,867 L 3548,867 L 3583,867 L 3618,867 L 3654,867 L 3689,865 L 3725,865 L 3760,865 L 3795,865 L 3831,865 L 3866,865 L 3902,865 L 3902,814 L 3866,814 L 3831,814 L 3795,814 L 3760,814 L 3725,814 L 3689,814 L 3654,816 L 3618,816 L 3583,816 L 3548,816 L 3512,816 L 3477,818 L 3441,818 L 3406,818 L 3371,818 L 3335,820 L 3300,820 L 3264,822 L 3229,822 L 3194,822 L 3194,873 Z\"/></svg>"
    }
   }
  },
  {
   "@context": "http://iiif.io/api/presentation/3/context.json",
   "id": "https://data.goldenagents.org/datasets/dh2020/annotation/A16098000171/r3l10",
   "type": "Annotation",
   "motivation": "supplementing",
   "body": [
    {
     "type": "TextualBody",
     "language": "nl",
     "value": "Een grote mout"
    }
   ],
   "target": {
    "id": "https://data.goldenagents.org/datasets/dh2020/canvas/A16098000171",
    "selector": {
     "type": "SvgSelector",
     "value": "<svg xmlns=\"http://www.w3.org/2000/svg\"><path fill-rule=\"evenodd\" fill=\"#66cc99\" stroke=\"#555555\" stroke-width=\"1\" fill-opacity=\"0.08\" d=\"M 3176,961 L 3211,957 L 3247,955 L 3283,954 L 3319,951 L 3355,951 L 3391,949 L 3427,949 L 3463,948 L 3499,947 L 3535,947 L 3570,945 L 3606,945 L 3642,943 L 3678,943 L 3714,941 L 3750,941 L 3786,939 L 3822,937 L 3858,935 L 3894,933 L 3894,882 L 3858,884 L 3822,886 L 3786,888 L 3750,890 L 3714,890 L 3678,892 L 3642,892 L 3606,894 L 3570,894 L 3535,896 L 3499,896 L 3463,897 L 3427,898 L 3391,898 L 3355,900 L 3319,900 L 3283,903 L 3247,904 L 3211,906 L 3176,910 L 3176,961 Z\"/></svg>"
    }
   }
  },
  {
   "@context": "http://iiif.io/api/presentation/3/context.json",
   "id": "https://data.goldenagents.org/datasets/dh2020/annotation/A16098000171/r3l11",
   "type": "Annotation",
   "motivation": "supplementing",
   "body": [
    {
     "type": "TextualBody",
     "language": "nl",
     "value": "Een kleijne mout"
    }
   ],
   "target": {
    "id": "https://data.goldenagents.org/datasets/dh2020/canvas/A16098000171",
    "selector": {
     "type": "SvgSelector",
     "value": "<svg xmlns=\"http://www.w3.org/2000/svg\"><path fill-rule=\"evenodd\" fill=\"#66cc99\" stroke=\"#555555\" stroke-width=\"1\" fill-opacity=\"0.08\" d=\"M 3176,1037 L 3216,1031 L 3257,1027 L 3297,1023 L 3338,1020 L 3378,1017 L 3419,1015 L 3459,1013 L 3500,1013 L 3540,1011 L 3581,1011 L 3621,1011 L 3662,1011 L 3702,1010 L 3743,1009 L 3783,1009 L 3824,1009 L 3864,1009 L 3905,1007 L 3945,1005 L 3986,1003 L 3986,963 L 3945,965 L 3905,967 L 3864,969 L 3824,969 L 3783,969 L 3743,969 L 3702,970 L 3662,971 L 3621,971 L 3581,971 L 3540,971 L 3500,973 L 3459,973 L 3419,975 L 3378,977 L 3338,980 L 3297,983 L 3257,987 L 3216,991 L 3176,997 L 3176,1037 Z\"/></svg>"
    }
   }
  },
  {
   "@context": "http://iiif.io/api/presentation/3/context.json",
   "id": "https://data.goldenagents.org/datasets/dh2020/annotation/A16098000171/r3l12",
   "type": "Annotation",
   "motivation": "supplementing",
   "body": [
    {
     "type": "TextualBody",
     "language": "nl",
     "value": "Een groene beugelstoel"
    }
   ],
   "target": {
    "id": "https://data.goldenagents.org/datasets/dh2020/canvas/A16098000171",
    "selector": {
     "type": "SvgSelector",
     "value": "<svg xmlns=\"http://www.w3.org/2000/svg\"><path fill-rule=\"evenodd\" fill=\"#66cc99\" stroke=\"#555555\" stroke-width=\"1\" fill-opacity=\"0.08\" d=\"M 3256,1083 L 3317,1085 L 3378,1089 L 3439,1091 L 3500,1091 L 3561,1091 L 3622,1091 L 3683,1091 L 3744,1089 L 3805,1087 L 3866,1085 L 3927,1083 L 3988,1079 L 4049,1077 L 4110,1075 L 4171,1073 L 4232,1072 L 4293,1071 L 4354,1071 L 4415,1071 L 4476,1071 L 4476,1031 L 4415,1031 L 4354,1031 L 4293,1031 L 4232,1032 L 4171,1033 L 4110,1035 L 4049,1037 L 3988,1039 L 3927,1043 L 3866,1045 L 3805,1047 L 3744,1049 L 3683,1051 L 3622,1051 L 3561,1051 L 3500,1051 L 3439,1051 L 3378,1049 L 3317,1045 L 3256,1043 L 3256,1083 Z\"/></svg>"
    }
   }
  },
  {
   "@context": "http://iiif.io/api/presentation/3/context.json",
   "id": "https://data.goldenagents.org/datasets/dh2020/annotation/A16098000171/r3l13",
   "type": "Annotation",
   "motivation": "supplementing",
   "body": [
    {
     "type": "TextualBody",
     "language": "nl",
     "value": "Een grote witte beschuijt"
    }
   ],
   "target": {
    "id": "https://data.goldenagents.org/datasets/dh2020/canvas/A16098000171",
    "selector": {
     "type": "SvgSelector",
     "value": "<svg xmlns=\"http://www.w3.org/2000/svg\"><path fill-rule=\"evenodd\" fill=\"#66cc99\" stroke=\"#555555\" stroke-width=\"1\" fill-opacity=\"0.08\" d=\"M 3144,1191 L 3206,1191 L 3268,1190 L 3331,1188 L 3393,1187 L 3456,1184 L 3518,1181 L 3580,1179 L 3643,1176 L 3705,1173 L 3768,1171 L 3830,1167 L 3892,1165 L 3955,1163 L 4017,1161 L 4080,1159 L 4142,1159 L 4204,1157 L 4267,1157 L 4329,1157 L 4392,1159 L 4392,1114 L 4329,1112 L 4267,1112 L 4204,1112 L 4142,1114 L 4080,1114 L 4017,1116 L 3955,1118 L 3892,1120 L 3830,1122 L 3768,1126 L 3705,1128 L 3643,1131 L 3580,1134 L 3518,1136 L 3456,1139 L 3393,1142 L 3331,1143 L 3268,1145 L 3206,1146 L 3144,1146 L 3144,1191 Z\"/></svg>"
    }
   }
  },
  {
   "@context": "http://iiif.io/api/presentation/3/context.json",
   "id": "https://data.goldenagents.org/datasets/dh2020/annotation/A16098000171/r3l14",
   "type": "Annotation",
   "motivation": "supplementing",
   "body": [
    {
     "type": "TextualBody",
     "language": "nl",
     "value": "ton met een dexel"
    }
   ],
   "target": {
    "id": "https://data.goldenagents.org/datasets/dh2020/canvas/A16098000171",
    "selector": {
     "type": "SvgSelector",
     "value": "<svg xmlns=\"http://www.w3.org/2000/svg\"><path fill-rule=\"evenodd\" fill=\"#66cc99\" stroke=\"#555555\" stroke-width=\"1\" fill-opacity=\"0.08\" d=\"M 3400,1247 L 3442,1249 L 3485,1251 L 3528,1251 L 3571,1251 L 3614,1250 L 3656,1249 L 3699,1247 L 3742,1245 L 3785,1243 L 3828,1241 L 3870,1241 L 3913,1239 L 3956,1239 L 3999,1239 L 4042,1239 L 4084,1240 L 4127,1243 L 4170,1245 L 4213,1251 L 4256,1257 L 4256,1212 L 4213,1206 L 4170,1200 L 4127,1198 L 4084,1195 L 4042,1194 L 3999,1194 L 3956,1194 L 3913,1194 L 3870,1196 L 3828,1196 L 3785,1198 L 3742,1200 L 3699,1202 L 3656,1204 L 3614,1205 L 3571,1206 L 3528,1206 L 3485,1206 L 3442,1204 L 3400,1202 L 3400,1247 Z\"/></svg>"
    }
   }
  },
  {
   "@context": "http://iiif.io/api/presentation/3/context.json",
   "id": "https://data.goldenagents.org/datasets/dh2020/annotation/A16098000171/r3l15",
   "type": "Annotation",
   "motivation": "supplementing",
   "body": [
    {
     "type": "TextualBody",
     "language": "nl",
     "value": "Een spinnewiel"
    }
   ],
   "target": {
    "id": "https://data.goldenagents.org/datasets/dh2020/canvas/A16098000171",
    "selector": {
     "type": "SvgSelector",
     "value": "<svg xmlns=\"http://www.w3.org/2000/svg\"><path fill-rule=\"evenodd\" fill=\"#66cc99\" stroke=\"#555555\" stroke-width=\"1\" fill-opacity=\"0.08\" d=\"M 3206,1352 L 3254,1355 L 3302,1358 L 3350,1358 L 3398,1358 L 3446,1358 L 3494,1356 L 3542,1354 L 3590,1352 L 3638,1350 L 3687,1348 L 3735,1346 L 3783,1344 L 3831,1342 L 3879,1342 L 3927,1340 L 3975,1341 L 4023,1342 L 4071,1346 L 4119,1349 L 4168,1354 L 4168,1293 L 4119,1288 L 4071,1285 L 4023,1281 L 3975,1280 L 3927,1279 L 3879,1281 L 3831,1281 L 3783,1283 L 3735,1285 L 3687,1287 L 3638,1289 L 3590,1291 L 3542,1293 L 3494,1295 L 3446,1297 L 3398,1297 L 3350,1297 L 3302,1297 L 3254,1294 L 3206,1291 L 3206,1352 Z\"/></svg>"
    }
   }
  },
  {
   "@context": "http://iiif.io/api/presentation/3/context.json",
   "id": "https://data.goldenagents.org/datasets/dh2020/annotation/A16098000171/r3l16",
   "type": "Annotation",
   "motivation": "supplementing",
   "body": [
    {
     "type": "TextualBody",
     "language": "nl",
     "value": "Aldus geinventariseert ende gespecificeert inden sterffhuijse"
    }
   ],
   "target": {
    "id": "https://data.goldenagents.org/datasets/dh2020/canvas/A16098000171",
    "selector": {
     "type": "SvgSelector",
     "value": "<svg xmlns=\"http://www.w3.org/2000/svg\"><path fill-rule=\"evenodd\" fill=\"#66cc99\" stroke=\"#555555\" stroke-width=\"1\" fill-opacity=\"0.08\" d=\"M 3120,1600 L 3213,1601 L 3307,1602 L 3400,1602 L 3494,1602 L 3587,1602 L 3681,1600 L 3774,1600 L 3868,1598 L 3961,1598 L 4055,1596 L 4148,1596 L 4242,1594 L 4335,1594 L 4429,1592 L 4522,1592 L 4616,1592 L 4709,1592 L 4803,1592 L 4896,1594 L 4990,1594 L 4990,1533 L 4896,1533 L 4803,1531 L 4709,1531 L 4616,1531 L 4522,1531 L 4429,1531 L 4335,1533 L 4242,1533 L 4148,1535 L 4055,1535 L 3961,1537 L 3868,1537 L 3774,1539 L 3681,1539 L 3587,1541 L 3494,1541 L 3400,1541 L 3307,1541 L 3213,1540 L 3120,1539 L 3120,1600 Z\"/></svg>"
    }
   }
  },
  {
   "@context": "http://iiif.io/api/presentation/3/context.json",
   "id": "https://data.goldenagents.org/datasets/dh2020/annotation/A16098000171/r3l17",
   "type": "Annotation",
   "motivation": "supplementing",
   "body": [
    {
     "type": "TextualBody",
     "language": "nl",
     "value": "vande voorn. Maria Boon-eters gestaan inde haarlemer\u00ac"
    }
   ],
   "target": {
    "id": "https://data.goldenagents.org/datasets/dh2020/canvas/A16098000171",
    "selector": {
     "type": "SvgSelector",
     "value": "<svg xmlns=\"http://www.w3.org/2000/svg\"><path fill-rule=\"evenodd\" fill=\"#66cc99\" stroke=\"#555555\" stroke-width=\"1\" fill-opacity=\"0.08\" d=\"M 3214,1698 L 3301,1696 L 3388,1694 L 3476,1693 L 3563,1690 L 3651,1689 L 3738,1688 L 3825,1686 L 3913,1684 L 4000,1682 L 4088,1681 L 4175,1680 L 4262,1678 L 4350,1678 L 4437,1676 L 4525,1676 L 4612,1676 L 4699,1674 L 4787,1674 L 4874,1674 L 4962,1676 L 4962,1615 L 4874,1613 L 4787,1613 L 4699,1613 L 4612,1615 L 4525,1615 L 4437,1615 L 4350,1617 L 4262,1617 L 4175,1619 L 4088,1620 L 4000,1621 L 3913,1623 L 3825,1625 L 3738,1627 L 3651,1628 L 3563,1629 L 3476,1632 L 3388,1633 L 3301,1635 L 3214,1637 L 3214,1698 Z\"/></svg>"
    }
   }
  },
  {
   "@context": "http://iiif.io/api/presentation/3/context.json",
   "id": "https://data.goldenagents.org/datasets/dh2020/annotation/A16098000171/r3l18",
   "type": "Annotation",
   "motivation": "supplementing",
   "body": [
    {
     "type": "TextualBody",
     "language": "nl",
     "value": "straat voorbij de eerste haarlemmer dwarsstraat"
    }
   ],
   "target": {
    "id": "https://data.goldenagents.org/datasets/dh2020/canvas/A16098000171",
    "selector": {
     "type": "SvgSelector",
     "value": "<svg xmlns=\"http://www.w3.org/2000/svg\"><path fill-rule=\"evenodd\" fill=\"#66cc99\" stroke=\"#555555\" stroke-width=\"1\" fill-opacity=\"0.08\" d=\"M 3202,1780 L 3288,1778 L 3374,1776 L 3460,1774 L 3546,1772 L 3632,1771 L 3718,1770 L 3804,1768 L 3890,1766 L 3976,1764 L 4062,1764 L 4148,1762 L 4234,1760 L 4320,1758 L 4406,1756 L 4492,1756 L 4578,1754 L 4664,1752 L 4750,1750 L 4836,1749 L 4922,1748 L 4922,1687 L 4836,1688 L 4750,1689 L 4664,1691 L 4578,1693 L 4492,1695 L 4406,1695 L 4320,1697 L 4234,1699 L 4148,1701 L 4062,1703 L 3976,1703 L 3890,1705 L 3804,1707 L 3718,1709 L 3632,1710 L 3546,1711 L 3460,1713 L 3374,1715 L 3288,1717 L 3202,1719 L 3202,1780 Z\"/></svg>"
    }
   }
  },
  {
   "@context": "http://iiif.io/api/presentation/3/context.json",
   "id": "https://data.goldenagents.org/datasets/dh2020/annotation/A16098000171/r3l19",
   "type": "Annotation",
   "motivation": "supplementing",
   "body": [
    {
     "type": "TextualBody",
     "language": "nl",
     "value": "binnen Amstelredamme, Bij mij Jacob de Winter Openbaar"
    }
   ],
   "target": {
    "id": "https://data.goldenagents.org/datasets/dh2020/canvas/A16098000171",
    "selector": {
     "type": "SvgSelector",
     "value": "<svg xmlns=\"http://www.w3.org/2000/svg\"><path fill-rule=\"evenodd\" fill=\"#66cc99\" stroke=\"#555555\" stroke-width=\"1\" fill-opacity=\"0.08\" d=\"M 3218,1862 L 3305,1862 L 3392,1860 L 3479,1860 L 3566,1858 L 3653,1856 L 3740,1856 L 3827,1854 L 3914,1852 L 4001,1850 L 4089,1848 L 4176,1846 L 4263,1844 L 4350,1844 L 4437,1842 L 4524,1840 L 4611,1840 L 4698,1838 L 4785,1838 L 4872,1838 L 4960,1838 L 4960,1783 L 4872,1783 L 4785,1783 L 4698,1783 L 4611,1785 L 4524,1785 L 4437,1787 L 4350,1789 L 4263,1789 L 4176,1791 L 4089,1793 L 4001,1795 L 3914,1797 L 3827,1799 L 3740,1801 L 3653,1801 L 3566,1803 L 3479,1805 L 3392,1805 L 3305,1807 L 3218,1807 L 3218,1862 Z\"/></svg>"
    }
   }
  },
  {
   "@context": "http://iiif.io/api/presentation/3/context.json",
   "id": "https://data.goldenagents.org/datasets/dh2020/annotation/A16098000171/r3l20",
   "type": "Annotation",
   "motivation": "supplementing",
   "body": [
    {
     "type": "TextualBody",
     "language": "nl",
     "value": "Desen"
    }
   ],
   "target": {
    "id": "https://data.goldenagents.org/datasets/dh2020/canvas/A16098000171",
    "selector": {
     "type": "SvgSelector",
     "value": "<svg xmlns=\"http://www.w3.org/2000/svg\"><path fill-rule=\"evenodd\" fill=\"#66cc99\" stroke=\"#555555\" stroke-width=\"1\" fill-opacity=\"0.08\" d=\"M 4682,1917 L 4707,1919 L 4732,1921 L 4758,1923 L 4783,1924 L 4809,1925 L 4834,1925 L 4859,1925 L 4885,1924 L 4910,1921 L 4936,1919 L 4936,1861 L 4910,1863 L 4885,1866 L 4859,1867 L 4834,1867 L 4809,1867 L 4783,1866 L 4758,1865 L 4732,1863 L 4707,1861 L 4682,1859 L 4682,1917 Z\"/></svg>"
    }
   }
  },
  {
   "@context": "http://iiif.io/api/presentation/3/context.json",
   "id": "https://data.goldenagents.org/datasets/dh2020/annotation/A16098000171/r3l21",
   "type": "Annotation",
   "motivation": "supplementing",
   "body": [
    {
     "type": "TextualBody",
     "language": "nl",
     "value": "Notaris binnen der selver stede residerende"
    }
   ],
   "target": {
    "id": "https://data.goldenagents.org/datasets/dh2020/canvas/A16098000171",
    "selector": {
     "type": "SvgSelector",
     "value": "<svg xmlns=\"http://www.w3.org/2000/svg\"><path fill-rule=\"evenodd\" fill=\"#66cc99\" stroke=\"#555555\" stroke-width=\"1\" fill-opacity=\"0.08\" d=\"M 3178,1962 L 3245,1960 L 3313,1956 L 3380,1954 L 3448,1952 L 3516,1948 L 3583,1946 L 3651,1944 L 3718,1941 L 3786,1939 L 3854,1937 L 3921,1934 L 3989,1932 L 4056,1930 L 4124,1928 L 4191,1925 L 4259,1923 L 4327,1922 L 4394,1919 L 4462,1916 L 4530,1914 L 4530,1859 L 4462,1861 L 4394,1864 L 4327,1867 L 4259,1868 L 4191,1870 L 4124,1873 L 4056,1875 L 3989,1877 L 3921,1879 L 3854,1882 L 3786,1884 L 3718,1886 L 3651,1889 L 3583,1891 L 3516,1893 L 3448,1897 L 3380,1899 L 3313,1901 L 3245,1905 L 3178,1907 L 3178,1962 Z\"/></svg>"
    }
   }
  },
  {
   "@context": "http://iiif.io/api/presentation/3/context.json",
   "id": "https://data.goldenagents.org/datasets/dh2020/annotation/A16098000171/r3l22",
   "type": "Annotation",
   "motivation": "supplementing",
   "body": [
    {
     "type": "TextualBody",
     "language": "nl",
     "value": "xxjx April ao. xvic drijenvijftigh, Ter presentie"
    }
   ],
   "target": {
    "id": "https://data.goldenagents.org/datasets/dh2020/canvas/A16098000171",
    "selector": {
     "type": "SvgSelector",
     "value": "<svg xmlns=\"http://www.w3.org/2000/svg\"><path fill-rule=\"evenodd\" fill=\"#66cc99\" stroke=\"#555555\" stroke-width=\"1\" fill-opacity=\"0.08\" d=\"M 3202,2049 L 3285,2043 L 3369,2037 L 3452,2033 L 3536,2029 L 3620,2027 L 3703,2023 L 3787,2021 L 3870,2019 L 3954,2018 L 4038,2017 L 4121,2015 L 4205,2015 L 4288,2013 L 4372,2013 L 4456,2011 L 4539,2011 L 4623,2009 L 4706,2007 L 4790,2004 L 4874,2001 L 4874,1944 L 4790,1947 L 4706,1950 L 4623,1952 L 4539,1954 L 4456,1954 L 4372,1956 L 4288,1956 L 4205,1958 L 4121,1958 L 4038,1960 L 3954,1961 L 3870,1962 L 3787,1964 L 3703,1966 L 3620,1970 L 3536,1972 L 3452,1976 L 3369,1980 L 3285,1986 L 3202,1992 L 3202,2049 Z\"/></svg>"
    }
   }
  },
  {
   "@context": "http://iiif.io/api/presentation/3/context.json",
   "id": "https://data.goldenagents.org/datasets/dh2020/annotation/A16098000171/r3l23",
   "type": "Annotation",
   "motivation": "supplementing",
   "body": [
    {
     "type": "TextualBody",
     "language": "nl",
     "value": "van Johannes Vis, ende Cornelis Kick poorteren deser"
    }
   ],
   "target": {
    "id": "https://data.goldenagents.org/datasets/dh2020/canvas/A16098000171",
    "selector": {
     "type": "SvgSelector",
     "value": "<svg xmlns=\"http://www.w3.org/2000/svg\"><path fill-rule=\"evenodd\" fill=\"#66cc99\" stroke=\"#555555\" stroke-width=\"1\" fill-opacity=\"0.08\" d=\"M 3204,2132 L 3288,2124 L 3373,2117 L 3458,2112 L 3542,2106 L 3627,2102 L 3712,2100 L 3796,2098 L 3881,2096 L 3966,2094 L 4051,2094 L 4135,2092 L 4220,2092 L 4305,2092 L 4389,2090 L 4474,2090 L 4559,2088 L 4643,2087 L 4728,2084 L 4813,2080 L 4898,2076 L 4898,2021 L 4813,2025 L 4728,2029 L 4643,2032 L 4559,2033 L 4474,2035 L 4389,2035 L 4305,2037 L 4220,2037 L 4135,2037 L 4051,2039 L 3966,2039 L 3881,2041 L 3796,2043 L 3712,2045 L 3627,2047 L 3542,2051 L 3458,2057 L 3373,2062 L 3288,2069 L 3204,2077 L 3204,2132 Z\"/></svg>"
    }
   }
  },
  {
   "@context": "http://iiif.io/api/presentation/3/context.json",
   "id": "https://data.goldenagents.org/datasets/dh2020/annotation/A16098000171/r3l24",
   "type": "Annotation",
   "motivation": "supplementing",
   "body": [
    {
     "type": "TextualBody",
     "language": "nl",
     "value": "Stede als getuijgen hier over gestaan."
    }
   ],
   "target": {
    "id": "https://data.goldenagents.org/datasets/dh2020/canvas/A16098000171",
    "selector": {
     "type": "SvgSelector",
     "value": "<svg xmlns=\"http://www.w3.org/2000/svg\"><path fill-rule=\"evenodd\" fill=\"#66cc99\" stroke=\"#555555\" stroke-width=\"1\" fill-opacity=\"0.08\" d=\"M 3202,2208 L 3270,2204 L 3338,2200 L 3406,2196 L 3474,2193 L 3542,2190 L 3610,2186 L 3678,2183 L 3746,2181 L 3814,2178 L 3882,2176 L 3950,2174 L 4018,2172 L 4086,2172 L 4154,2170 L 4222,2168 L 4290,2168 L 4358,2166 L 4426,2164 L 4494,2164 L 4562,2162 L 4562,2107 L 4494,2109 L 4426,2109 L 4358,2111 L 4290,2113 L 4222,2113 L 4154,2115 L 4086,2117 L 4018,2117 L 3950,2119 L 3882,2121 L 3814,2123 L 3746,2126 L 3678,2128 L 3610,2131 L 3542,2135 L 3474,2138 L 3406,2141 L 3338,2145 L 3270,2149 L 3202,2153 L 3202,2208 Z\"/></svg>"
    }
   }
  },
  {
   "@context": "http://iiif.io/api/presentation/3/context.json",
   "id": "https://data.goldenagents.org/datasets/dh2020/annotation/A16098000171/r3l25",
   "type": "Annotation",
   "motivation": "supplementing",
   "body": [
    {
     "type": "TextualBody",
     "language": "nl",
     "value": "Johannes Vis  Cornelis Kick"
    }
   ],
   "target": {
    "id": "https://data.goldenagents.org/datasets/dh2020/canvas/A16098000171",
    "selector": {
     "type": "SvgSelector",
     "value": "<svg xmlns=\"http://www.w3.org/2000/svg\"><path fill-rule=\"evenodd\" fill=\"#66cc99\" stroke=\"#555555\" stroke-width=\"1\" fill-opacity=\"0.08\" d=\"M 3614,2380 L 3675,2374 L 3736,2370 L 3798,2366 L 3859,2363 L 3921,2361 L 3982,2360 L 4043,2360 L 4105,2358 L 4166,2358 L 4228,2358 L 4289,2358 L 4350,2358 L 4412,2358 L 4473,2357 L 4535,2356 L 4596,2353 L 4657,2350 L 4719,2347 L 4780,2342 L 4842,2338 L 4842,2277 L 4780,2281 L 4719,2286 L 4657,2289 L 4596,2292 L 4535,2295 L 4473,2296 L 4412,2297 L 4350,2297 L 4289,2297 L 4228,2297 L 4166,2297 L 4105,2297 L 4043,2299 L 3982,2299 L 3921,2300 L 3859,2302 L 3798,2305 L 3736,2309 L 3675,2313 L 3614,2319 L 3614,2380 Z\"/></svg>"
    }
   }
  },
  {
   "@context": "http://iiif.io/api/presentation/3/context.json",
   "id": "https://data.goldenagents.org/datasets/dh2020/annotation/A16098000171/r3l26",
   "type": "Annotation",
   "motivation": "supplementing",
   "body": [
    {
     "type": "TextualBody",
     "language": "nl",
     "value": "Testor"
    }
   ],
   "target": {
    "id": "https://data.goldenagents.org/datasets/dh2020/canvas/A16098000171",
    "selector": {
     "type": "SvgSelector",
     "value": "<svg xmlns=\"http://www.w3.org/2000/svg\"><path fill-rule=\"evenodd\" fill=\"#66cc99\" stroke=\"#555555\" stroke-width=\"1\" fill-opacity=\"0.08\" d=\"M 4520,2490 L 4546,2485 L 4573,2482 L 4599,2479 L 4626,2478 L 4652,2476 L 4679,2474 L 4705,2473 L 4732,2472 L 4758,2471 L 4785,2470 L 4811,2470 L 4838,2468 L 4838,2407 L 4811,2409 L 4785,2409 L 4758,2410 L 4732,2411 L 4705,2412 L 4679,2413 L 4652,2415 L 4626,2417 L 4599,2418 L 4573,2421 L 4546,2424 L 4520,2429 L 4520,2490 Z\"/></svg>"
    }
   }
  },
  {
   "@context": "http://iiif.io/api/presentation/3/context.json",
   "id": "https://data.goldenagents.org/datasets/dh2020/annotation/A16098000171/r3l27",
   "type": "Annotation",
   "motivation": "supplementing",
   "body": [
    {
     "type": "TextualBody",
     "language": "nl",
     "value": "J:de Winter N.P."
    }
   ],
   "target": {
    "id": "https://data.goldenagents.org/datasets/dh2020/canvas/A16098000171",
    "selector": {
     "type": "SvgSelector",
     "value": "<svg xmlns=\"http://www.w3.org/2000/svg\"><path fill-rule=\"evenodd\" fill=\"#66cc99\" stroke=\"#555555\" stroke-width=\"1\" fill-opacity=\"0.08\" d=\"M 4226,2652 L 4262,2651 L 4299,2650 L 4335,2647 L 4372,2644 L 4409,2640 L 4445,2637 L 4482,2634 L 4518,2629 L 4555,2625 L 4592,2623 L 4628,2620 L 4665,2618 L 4701,2616 L 4738,2616 L 4775,2616 L 4811,2618 L 4848,2619 L 4884,2624 L 4921,2631 L 4958,2638 L 4958,2577 L 4921,2570 L 4884,2563 L 4848,2558 L 4811,2557 L 4775,2555 L 4738,2555 L 4701,2555 L 4665,2557 L 4628,2559 L 4592,2562 L 4555,2564 L 4518,2568 L 4482,2573 L 4445,2576 L 4409,2579 L 4372,2583 L 4335,2586 L 4299,2589 L 4262,2590 L 4226,2591 L 4226,2652 Z\"/></svg>"
    }
   }
  }
 ]
}